{
  "schema_version": "analytics-v1",
  "generated_at": "2026-07-14T23:00:31Z",
  "all_time_summary": {
    "jobs": 5215,
    "completed_jobs": 3507,
    "failed_jobs": 1708,
    "cpu_hours_allocated": 65736.519444,
    "measured_cpu_hours": 0.0,
    "avg_cpu_efficiency": null,
    "jobs_with_measured_cpu": 0,
    "requested_mem_gb_hours": 165260.919498,
    "measured_mem_gb_max_sum": 0.0,
    "avg_memory_efficiency": null,
    "jobs_with_measured_memory": 0,
    "estimated_cost_dkk": 4415.470119,
    "underutilized_cost_dkk": 0.0,
    "gpu_hours": 0.0,
    "cpu_cost_dkk": 4272.873764,
    "mem_cost_dkk": 2685.489942,
    "gpu_cost_dkk": 0.0,
    "cost_bearer": "cpu",
    "cost_bearer_cost_dkk": 4272.873764,
    "cost_bearer_efficiency": null,
    "cost_bearer_waste_dkk": 0.0,
    "leaf_index": null,
    "leaf_index_components": []
  },
  "rolling_summaries": {
    "7d": {
      "jobs": 0,
      "completed_jobs": 0,
      "failed_jobs": 0,
      "cpu_hours_allocated": 0.0,
      "measured_cpu_hours": 0.0,
      "avg_cpu_efficiency": null,
      "jobs_with_measured_cpu": 0,
      "requested_mem_gb_hours": 0.0,
      "measured_mem_gb_max_sum": 0.0,
      "avg_memory_efficiency": null,
      "jobs_with_measured_memory": 0,
      "estimated_cost_dkk": 0.0,
      "underutilized_cost_dkk": 0.0,
      "gpu_hours": 0.0,
      "cpu_cost_dkk": 0.0,
      "mem_cost_dkk": 0.0,
      "gpu_cost_dkk": 0.0,
      "cost_bearer": "cpu",
      "cost_bearer_cost_dkk": 0.0,
      "cost_bearer_efficiency": null,
      "cost_bearer_waste_dkk": 0.0,
      "leaf_index": null,
      "leaf_index_components": []
    },
    "30d": {
      "jobs": 0,
      "completed_jobs": 0,
      "failed_jobs": 0,
      "cpu_hours_allocated": 0.0,
      "measured_cpu_hours": 0.0,
      "avg_cpu_efficiency": null,
      "jobs_with_measured_cpu": 0,
      "requested_mem_gb_hours": 0.0,
      "measured_mem_gb_max_sum": 0.0,
      "avg_memory_efficiency": null,
      "jobs_with_measured_memory": 0,
      "estimated_cost_dkk": 0.0,
      "underutilized_cost_dkk": 0.0,
      "gpu_hours": 0.0,
      "cpu_cost_dkk": 0.0,
      "mem_cost_dkk": 0.0,
      "gpu_cost_dkk": 0.0,
      "cost_bearer": "cpu",
      "cost_bearer_cost_dkk": 0.0,
      "cost_bearer_efficiency": null,
      "cost_bearer_waste_dkk": 0.0,
      "leaf_index": null,
      "leaf_index_components": []
    },
    "90d": {
      "jobs": 0,
      "completed_jobs": 0,
      "failed_jobs": 0,
      "cpu_hours_allocated": 0.0,
      "measured_cpu_hours": 0.0,
      "avg_cpu_efficiency": null,
      "jobs_with_measured_cpu": 0,
      "requested_mem_gb_hours": 0.0,
      "measured_mem_gb_max_sum": 0.0,
      "avg_memory_efficiency": null,
      "jobs_with_measured_memory": 0,
      "estimated_cost_dkk": 0.0,
      "underutilized_cost_dkk": 0.0,
      "gpu_hours": 0.0,
      "cpu_cost_dkk": 0.0,
      "mem_cost_dkk": 0.0,
      "gpu_cost_dkk": 0.0,
      "cost_bearer": "cpu",
      "cost_bearer_cost_dkk": 0.0,
      "cost_bearer_efficiency": null,
      "cost_bearer_waste_dkk": 0.0,
      "leaf_index": null,
      "leaf_index_components": []
    },
    "180d": {
      "jobs": 40,
      "completed_jobs": 10,
      "failed_jobs": 30,
      "cpu_hours_allocated": 210.040556,
      "measured_cpu_hours": 0.0,
      "avg_cpu_efficiency": null,
      "jobs_with_measured_cpu": 0,
      "requested_mem_gb_hours": 1692.866667,
      "measured_mem_gb_max_sum": 0.0,
      "avg_memory_efficiency": null,
      "jobs_with_measured_memory": 0,
      "estimated_cost_dkk": 27.510419,
      "underutilized_cost_dkk": 0.0,
      "gpu_hours": 0.0,
      "cpu_cost_dkk": 13.652636,
      "mem_cost_dkk": 27.509083,
      "gpu_cost_dkk": 0.0,
      "cost_bearer": "memory",
      "cost_bearer_cost_dkk": 27.509083,
      "cost_bearer_efficiency": null,
      "cost_bearer_waste_dkk": 0.0,
      "leaf_index": null,
      "leaf_index_components": []
    }
  },
  "daily_trends": [
    {
      "report_date": "2025-05-06",
      "avg_cpu_efficiency": null,
      "avg_memory_efficiency": null,
      "estimated_cost_dkk": 9.576233333333334,
      "underutilized_cost_dkk": 0.0,
      "gpu_hours": 0.0,
      "jobs": 35,
      "jobs_with_measured_cpu": 0,
      "jobs_with_measured_memory": 0,
      "cpu_hours_allocated": 147.32666666666665,
      "measured_cpu_hours": 0.0,
      "requested_mem_gb_hours": 310.4577777777778,
      "measured_mem_gb_max_sum": 0.0
    },
    {
      "report_date": "2025-05-07",
      "avg_cpu_efficiency": null,
      "avg_memory_efficiency": null,
      "estimated_cost_dkk": 40.883411111111116,
      "underutilized_cost_dkk": 0.0,
      "gpu_hours": 0.0,
      "jobs": 35,
      "jobs_with_measured_cpu": 0,
      "jobs_with_measured_memory": 0,
      "cpu_hours_allocated": 628.9755555555555,
      "measured_cpu_hours": 0.0,
      "requested_mem_gb_hours": 1831.404444444444,
      "measured_mem_gb_max_sum": 0.0
    },
    {
      "report_date": "2025-05-08",
      "avg_cpu_efficiency": null,
      "avg_memory_efficiency": null,
      "estimated_cost_dkk": 30.262411111111117,
      "underutilized_cost_dkk": 0.0,
      "gpu_hours": 0.0,
      "jobs": 63,
      "jobs_with_measured_cpu": 0,
      "jobs_with_measured_memory": 0,
      "cpu_hours_allocated": 465.5755555555555,
      "measured_cpu_hours": 0.0,
      "requested_mem_gb_hours": 1241.533333333333,
      "measured_mem_gb_max_sum": 0.0
    },
    {
      "report_date": "2025-05-09",
      "avg_cpu_efficiency": null,
      "avg_memory_efficiency": null,
      "estimated_cost_dkk": 138.59327083333318,
      "underutilized_cost_dkk": 0.0,
      "gpu_hours": 0.0,
      "jobs": 151,
      "jobs_with_measured_cpu": 0,
      "jobs_with_measured_memory": 0,
      "cpu_hours_allocated": 2132.2041666666664,
      "measured_cpu_hours": 0.0,
      "requested_mem_gb_hours": 5685.968888888885,
      "measured_mem_gb_max_sum": 0.0
    },
    {
      "report_date": "2025-05-10",
      "avg_cpu_efficiency": null,
      "avg_memory_efficiency": null,
      "estimated_cost_dkk": 1239.0025194444447,
      "underutilized_cost_dkk": 0.0,
      "gpu_hours": 0.0,
      "jobs": 72,
      "jobs_with_measured_cpu": 0,
      "jobs_with_measured_memory": 0,
      "cpu_hours_allocated": 19061.577222222233,
      "measured_cpu_hours": 0.0,
      "requested_mem_gb_hours": 50842.45444444443,
      "measured_mem_gb_max_sum": 0.0
    },
    {
      "report_date": "2025-05-12",
      "avg_cpu_efficiency": null,
      "avg_memory_efficiency": null,
      "estimated_cost_dkk": 53.24561666666667,
      "underutilized_cost_dkk": 0.0,
      "gpu_hours": 0.0,
      "jobs": 508,
      "jobs_with_measured_cpu": 0,
      "jobs_with_measured_memory": 0,
      "cpu_hours_allocated": 819.1633333333335,
      "measured_cpu_hours": 0.0,
      "requested_mem_gb_hours": 2428.662222222223,
      "measured_mem_gb_max_sum": 0.0
    },
    {
      "report_date": "2025-05-13",
      "avg_cpu_efficiency": null,
      "avg_memory_efficiency": null,
      "estimated_cost_dkk": 44.383155555555554,
      "underutilized_cost_dkk": 0.0,
      "gpu_hours": 0.0,
      "jobs": 87,
      "jobs_with_measured_cpu": 0,
      "jobs_with_measured_memory": 0,
      "cpu_hours_allocated": 682.8177777777779,
      "measured_cpu_hours": 0.0,
      "requested_mem_gb_hours": 1544.6222222222216,
      "measured_mem_gb_max_sum": 0.0
    },
    {
      "report_date": "2025-05-14",
      "avg_cpu_efficiency": null,
      "avg_memory_efficiency": null,
      "estimated_cost_dkk": 25.83721111111117,
      "underutilized_cost_dkk": 0.0,
      "gpu_hours": 0.0,
      "jobs": 115,
      "jobs_with_measured_cpu": 0,
      "jobs_with_measured_memory": 0,
      "cpu_hours_allocated": 397.49555555555537,
      "measured_cpu_hours": 0.0,
      "requested_mem_gb_hours": 801.8844444444456,
      "measured_mem_gb_max_sum": 0.0
    },
    {
      "report_date": "2025-05-15",
      "avg_cpu_efficiency": null,
      "avg_memory_efficiency": null,
      "estimated_cost_dkk": 4.185927777777778,
      "underutilized_cost_dkk": 0.0,
      "gpu_hours": 0.0,
      "jobs": 46,
      "jobs_with_measured_cpu": 0,
      "jobs_with_measured_memory": 0,
      "cpu_hours_allocated": 16.29444444444445,
      "measured_cpu_hours": 0.0,
      "requested_mem_gb_hours": 257.2133333333329,
      "measured_mem_gb_max_sum": 0.0
    },
    {
      "report_date": "2025-05-16",
      "avg_cpu_efficiency": null,
      "avg_memory_efficiency": null,
      "estimated_cost_dkk": 6.011525,
      "underutilized_cost_dkk": 0.0,
      "gpu_hours": 0.0,
      "jobs": 25,
      "jobs_with_measured_cpu": 0,
      "jobs_with_measured_memory": 0,
      "cpu_hours_allocated": 71.49944444444445,
      "measured_cpu_hours": 0.0,
      "requested_mem_gb_hours": 353.87277777777774,
      "measured_mem_gb_max_sum": 0.0
    },
    {
      "report_date": "2025-05-19",
      "avg_cpu_efficiency": null,
      "avg_memory_efficiency": null,
      "estimated_cost_dkk": 0.017550000000000003,
      "underutilized_cost_dkk": 0.0,
      "gpu_hours": 0.0,
      "jobs": 54,
      "jobs_with_measured_cpu": 0,
      "jobs_with_measured_memory": 0,
      "cpu_hours_allocated": 0.26999999999999996,
      "measured_cpu_hours": 0.0,
      "requested_mem_gb_hours": 0.7199999999999999,
      "measured_mem_gb_max_sum": 0.0
    },
    {
      "report_date": "2025-05-20",
      "avg_cpu_efficiency": null,
      "avg_memory_efficiency": null,
      "estimated_cost_dkk": 0.03314999999999999,
      "underutilized_cost_dkk": 0.0,
      "gpu_hours": 0.0,
      "jobs": 56,
      "jobs_with_measured_cpu": 0,
      "jobs_with_measured_memory": 0,
      "cpu_hours_allocated": 0.5100000000000002,
      "measured_cpu_hours": 0.0,
      "requested_mem_gb_hours": 1.3600000000000005,
      "measured_mem_gb_max_sum": 0.0
    },
    {
      "report_date": "2025-05-26",
      "avg_cpu_efficiency": null,
      "avg_memory_efficiency": null,
      "estimated_cost_dkk": 18.11225,
      "underutilized_cost_dkk": 0.0,
      "gpu_hours": 0.0,
      "jobs": 126,
      "jobs_with_measured_cpu": 0,
      "jobs_with_measured_memory": 0,
      "cpu_hours_allocated": 278.65,
      "measured_cpu_hours": 0.0,
      "requested_mem_gb_hours": 614.4466666666668,
      "measured_mem_gb_max_sum": 0.0
    },
    {
      "report_date": "2025-05-27",
      "avg_cpu_efficiency": null,
      "avg_memory_efficiency": null,
      "estimated_cost_dkk": 47.50985416666667,
      "underutilized_cost_dkk": 0.0,
      "gpu_hours": 0.0,
      "jobs": 101,
      "jobs_with_measured_cpu": 0,
      "jobs_with_measured_memory": 0,
      "cpu_hours_allocated": 562.7491666666667,
      "measured_cpu_hours": 0.0,
      "requested_mem_gb_hours": 2773.3900000000003,
      "measured_mem_gb_max_sum": 0.0
    },
    {
      "report_date": "2025-05-28",
      "avg_cpu_efficiency": null,
      "avg_memory_efficiency": null,
      "estimated_cost_dkk": 58.4170166666667,
      "underutilized_cost_dkk": 0.0,
      "gpu_hours": 0.0,
      "jobs": 93,
      "jobs_with_measured_cpu": 0,
      "jobs_with_measured_memory": 0,
      "cpu_hours_allocated": 675.0266666666664,
      "measured_cpu_hours": 0.0,
      "requested_mem_gb_hours": 3589.6444444444446,
      "measured_mem_gb_max_sum": 0.0
    },
    {
      "report_date": "2025-05-29",
      "avg_cpu_efficiency": null,
      "avg_memory_efficiency": null,
      "estimated_cost_dkk": 76.76110000000001,
      "underutilized_cost_dkk": 0.0,
      "gpu_hours": 0.0,
      "jobs": 1,
      "jobs_with_measured_cpu": 0,
      "jobs_with_measured_memory": 0,
      "cpu_hours_allocated": 885.7049999999999,
      "measured_cpu_hours": 0.0,
      "requested_mem_gb_hours": 4723.76,
      "measured_mem_gb_max_sum": 0.0
    },
    {
      "report_date": "2025-05-31",
      "avg_cpu_efficiency": null,
      "avg_memory_efficiency": null,
      "estimated_cost_dkk": 149.7665,
      "underutilized_cost_dkk": 0.0,
      "gpu_hours": 0.0,
      "jobs": 1,
      "jobs_with_measured_cpu": 0,
      "jobs_with_measured_memory": 0,
      "cpu_hours_allocated": 1728.0749999999998,
      "measured_cpu_hours": 0.0,
      "requested_mem_gb_hours": 9216.4,
      "measured_mem_gb_max_sum": 0.0
    },
    {
      "report_date": "2025-06-05",
      "avg_cpu_efficiency": null,
      "avg_memory_efficiency": null,
      "estimated_cost_dkk": 107.46580000000002,
      "underutilized_cost_dkk": 0.0,
      "gpu_hours": 0.0,
      "jobs": 1,
      "jobs_with_measured_cpu": 0,
      "jobs_with_measured_memory": 0,
      "cpu_hours_allocated": 1239.99,
      "measured_cpu_hours": 0.0,
      "requested_mem_gb_hours": 6613.280000000001,
      "measured_mem_gb_max_sum": 0.0
    },
    {
      "report_date": "2025-07-04",
      "avg_cpu_efficiency": null,
      "avg_memory_efficiency": null,
      "estimated_cost_dkk": 60.00027222222223,
      "underutilized_cost_dkk": 0.0,
      "gpu_hours": 0.0,
      "jobs": 496,
      "jobs_with_measured_cpu": 0,
      "jobs_with_measured_memory": 0,
      "cpu_hours_allocated": 923.0811111111111,
      "measured_cpu_hours": 0.0,
      "requested_mem_gb_hours": 1789.4422222222224,
      "measured_mem_gb_max_sum": 0.0
    },
    {
      "report_date": "2025-07-05",
      "avg_cpu_efficiency": null,
      "avg_memory_efficiency": null,
      "estimated_cost_dkk": 124.2987777777776,
      "underutilized_cost_dkk": 0.0,
      "gpu_hours": 0.0,
      "jobs": 38,
      "jobs_with_measured_cpu": 0,
      "jobs_with_measured_memory": 0,
      "cpu_hours_allocated": 1912.2888888888908,
      "measured_cpu_hours": 0.0,
      "requested_mem_gb_hours": 3824.5777777777816,
      "measured_mem_gb_max_sum": 0.0
    },
    {
      "report_date": "2025-07-07",
      "avg_cpu_efficiency": null,
      "avg_memory_efficiency": null,
      "estimated_cost_dkk": 129.32999444444448,
      "underutilized_cost_dkk": 0.0,
      "gpu_hours": 0.0,
      "jobs": 263,
      "jobs_with_measured_cpu": 0,
      "jobs_with_measured_memory": 0,
      "cpu_hours_allocated": 1989.6922222222238,
      "measured_cpu_hours": 0.0,
      "requested_mem_gb_hours": 1790.772222222223,
      "measured_mem_gb_max_sum": 0.0
    },
    {
      "report_date": "2025-07-08",
      "avg_cpu_efficiency": null,
      "avg_memory_efficiency": null,
      "estimated_cost_dkk": 304.9009166666662,
      "underutilized_cost_dkk": 0.0,
      "gpu_hours": 0.0,
      "jobs": 420,
      "jobs_with_measured_cpu": 0,
      "jobs_with_measured_memory": 0,
      "cpu_hours_allocated": 4690.783333333347,
      "measured_cpu_hours": 0.0,
      "requested_mem_gb_hours": 8981.868888888852,
      "measured_mem_gb_max_sum": 0.0
    },
    {
      "report_date": "2025-07-09",
      "avg_cpu_efficiency": null,
      "avg_memory_efficiency": null,
      "estimated_cost_dkk": 240.71854444444455,
      "underutilized_cost_dkk": 0.0,
      "gpu_hours": 0.0,
      "jobs": 110,
      "jobs_with_measured_cpu": 0,
      "jobs_with_measured_memory": 0,
      "cpu_hours_allocated": 3703.3622222222193,
      "measured_cpu_hours": 0.0,
      "requested_mem_gb_hours": 7406.73222222222,
      "measured_mem_gb_max_sum": 0.0
    },
    {
      "report_date": "2025-07-10",
      "avg_cpu_efficiency": null,
      "avg_memory_efficiency": null,
      "estimated_cost_dkk": 1.2849958333333404,
      "underutilized_cost_dkk": 0.0,
      "gpu_hours": 0.0,
      "jobs": 824,
      "jobs_with_measured_cpu": 0,
      "jobs_with_measured_memory": 0,
      "cpu_hours_allocated": 19.769166666666692,
      "measured_cpu_hours": 0.0,
      "requested_mem_gb_hours": 29.65722222222231,
      "measured_mem_gb_max_sum": 0.0
    },
    {
      "report_date": "2025-07-11",
      "avg_cpu_efficiency": null,
      "avg_memory_efficiency": null,
      "estimated_cost_dkk": 68.37711111111116,
      "underutilized_cost_dkk": 0.0,
      "gpu_hours": 0.0,
      "jobs": 121,
      "jobs_with_measured_cpu": 0,
      "jobs_with_measured_memory": 0,
      "cpu_hours_allocated": 1051.9555555555555,
      "measured_cpu_hours": 0.0,
      "requested_mem_gb_hours": 1097.208888888888,
      "measured_mem_gb_max_sum": 0.0
    },
    {
      "report_date": "2025-07-12",
      "avg_cpu_efficiency": null,
      "avg_memory_efficiency": null,
      "estimated_cost_dkk": 91.13057777777777,
      "underutilized_cost_dkk": 0.0,
      "gpu_hours": 0.0,
      "jobs": 1,
      "jobs_with_measured_cpu": 0,
      "jobs_with_measured_memory": 0,
      "cpu_hours_allocated": 1402.0088888888888,
      "measured_cpu_hours": 0.0,
      "requested_mem_gb_hours": 2804.0177777777776,
      "measured_mem_gb_max_sum": 0.0
    },
    {
      "report_date": "2025-07-13",
      "avg_cpu_efficiency": null,
      "avg_memory_efficiency": null,
      "estimated_cost_dkk": 137.01017777777778,
      "underutilized_cost_dkk": 0.0,
      "gpu_hours": 0.0,
      "jobs": 1,
      "jobs_with_measured_cpu": 0,
      "jobs_with_measured_memory": 0,
      "cpu_hours_allocated": 2107.8488888888887,
      "measured_cpu_hours": 0.0,
      "requested_mem_gb_hours": 4215.697777777777,
      "measured_mem_gb_max_sum": 0.0
    },
    {
      "report_date": "2025-07-15",
      "avg_cpu_efficiency": null,
      "avg_memory_efficiency": null,
      "estimated_cost_dkk": 249.60635555555558,
      "underutilized_cost_dkk": 0.0,
      "gpu_hours": 0.0,
      "jobs": 1,
      "jobs_with_measured_cpu": 0,
      "jobs_with_measured_memory": 0,
      "cpu_hours_allocated": 3840.097777777778,
      "measured_cpu_hours": 0.0,
      "requested_mem_gb_hours": 7680.195555555556,
      "measured_mem_gb_max_sum": 0.0
    },
    {
      "report_date": "2025-07-28",
      "avg_cpu_efficiency": null,
      "avg_memory_efficiency": null,
      "estimated_cost_dkk": 0.16495555555555552,
      "underutilized_cost_dkk": 0.0,
      "gpu_hours": 0.0,
      "jobs": 67,
      "jobs_with_measured_cpu": 0,
      "jobs_with_measured_memory": 0,
      "cpu_hours_allocated": 2.537777777777779,
      "measured_cpu_hours": 0.0,
      "requested_mem_gb_hours": 4.589444444444447,
      "measured_mem_gb_max_sum": 0.0
    },
    {
      "report_date": "2025-07-29",
      "avg_cpu_efficiency": null,
      "avg_memory_efficiency": null,
      "estimated_cost_dkk": 0.8112722222222223,
      "underutilized_cost_dkk": 0.0,
      "gpu_hours": 0.0,
      "jobs": 9,
      "jobs_with_measured_cpu": 0,
      "jobs_with_measured_memory": 0,
      "cpu_hours_allocated": 12.481111111111112,
      "measured_cpu_hours": 0.0,
      "requested_mem_gb_hours": 12.50888888888889,
      "measured_mem_gb_max_sum": 0.0
    },
    {
      "report_date": "2025-07-30",
      "avg_cpu_efficiency": null,
      "avg_memory_efficiency": null,
      "estimated_cost_dkk": 0.03437777777777777,
      "underutilized_cost_dkk": 0.0,
      "gpu_hours": 0.0,
      "jobs": 3,
      "jobs_with_measured_cpu": 0,
      "jobs_with_measured_memory": 0,
      "cpu_hours_allocated": 0.5288888888888889,
      "measured_cpu_hours": 0.0,
      "requested_mem_gb_hours": 1.0577777777777777,
      "measured_mem_gb_max_sum": 0.0
    },
    {
      "report_date": "2025-08-03",
      "avg_cpu_efficiency": null,
      "avg_memory_efficiency": null,
      "estimated_cost_dkk": 420.89493333333337,
      "underutilized_cost_dkk": 0.0,
      "gpu_hours": 0.0,
      "jobs": 1,
      "jobs_with_measured_cpu": 0,
      "jobs_with_measured_memory": 0,
      "cpu_hours_allocated": 6475.306666666667,
      "measured_cpu_hours": 0.0,
      "requested_mem_gb_hours": 16727.875555555558,
      "measured_mem_gb_max_sum": 0.0
    },
    {
      "report_date": "2025-08-08",
      "avg_cpu_efficiency": null,
      "avg_memory_efficiency": null,
      "estimated_cost_dkk": 8.767777777777779,
      "underutilized_cost_dkk": 0.0,
      "gpu_hours": 0.0,
      "jobs": 23,
      "jobs_with_measured_cpu": 0,
      "jobs_with_measured_memory": 0,
      "cpu_hours_allocated": 134.88888888888889,
      "measured_cpu_hours": 0.0,
      "requested_mem_gb_hours": 67.44444444444444,
      "measured_mem_gb_max_sum": 0.0
    },
    {
      "report_date": "2025-08-11",
      "avg_cpu_efficiency": null,
      "avg_memory_efficiency": null,
      "estimated_cost_dkk": 0.4114504496256511,
      "underutilized_cost_dkk": 0.0,
      "gpu_hours": 0.0,
      "jobs": 1,
      "jobs_with_measured_cpu": 0,
      "jobs_with_measured_memory": 0,
      "cpu_hours_allocated": 4.938611111111111,
      "measured_cpu_hours": 0.0,
      "requested_mem_gb_hours": 25.320027669270836,
      "measured_mem_gb_max_sum": 0.0
    },
    {
      "report_date": "2025-08-12",
      "avg_cpu_efficiency": null,
      "avg_memory_efficiency": null,
      "estimated_cost_dkk": 21.539706929524744,
      "underutilized_cost_dkk": 0.0,
      "gpu_hours": 0.0,
      "jobs": 36,
      "jobs_with_measured_cpu": 0,
      "jobs_with_measured_memory": 0,
      "cpu_hours_allocated": 329.24499999999995,
      "measured_cpu_hours": 0.0,
      "requested_mem_gb_hours": 835.3448708767361,
      "measured_mem_gb_max_sum": 0.0
    },
    {
      "report_date": "2025-08-13",
      "avg_cpu_efficiency": null,
      "avg_memory_efficiency": null,
      "estimated_cost_dkk": 0.47490717569986984,
      "underutilized_cost_dkk": 0.0,
      "gpu_hours": 0.0,
      "jobs": 1,
      "jobs_with_measured_cpu": 0,
      "jobs_with_measured_memory": 0,
      "cpu_hours_allocated": 5.700277777777778,
      "measured_cpu_hours": 0.0,
      "requested_mem_gb_hours": 29.225056966145836,
      "measured_mem_gb_max_sum": 0.0
    },
    {
      "report_date": "2025-08-14",
      "avg_cpu_efficiency": null,
      "avg_memory_efficiency": null,
      "estimated_cost_dkk": 1.6495362657335098,
      "underutilized_cost_dkk": 0.0,
      "gpu_hours": 0.0,
      "jobs": 127,
      "jobs_with_measured_cpu": 0,
      "jobs_with_measured_memory": 0,
      "cpu_hours_allocated": 21.14111111111111,
      "measured_cpu_hours": 0.0,
      "requested_mem_gb_hours": 83.02159071180556,
      "measured_mem_gb_max_sum": 0.0
    },
    {
      "report_date": "2025-08-15",
      "avg_cpu_efficiency": null,
      "avg_memory_efficiency": null,
      "estimated_cost_dkk": 0.7301920572916667,
      "underutilized_cost_dkk": 0.0,
      "gpu_hours": 0.0,
      "jobs": 2,
      "jobs_with_measured_cpu": 0,
      "jobs_with_measured_memory": 0,
      "cpu_hours_allocated": 8.764444444444445,
      "measured_cpu_hours": 0.0,
      "requested_mem_gb_hours": 44.934895833333336,
      "measured_mem_gb_max_sum": 0.0
    },
    {
      "report_date": "2025-08-18",
      "avg_cpu_efficiency": null,
      "avg_memory_efficiency": null,
      "estimated_cost_dkk": 1.0693944444444445,
      "underutilized_cost_dkk": 0.0,
      "gpu_hours": 0.0,
      "jobs": 109,
      "jobs_with_measured_cpu": 0,
      "jobs_with_measured_memory": 0,
      "cpu_hours_allocated": 15.853333333333344,
      "measured_cpu_hours": 0.0,
      "requested_mem_gb_hours": 49.79111111111113,
      "measured_mem_gb_max_sum": 0.0
    },
    {
      "report_date": "2025-08-19",
      "avg_cpu_efficiency": null,
      "avg_memory_efficiency": null,
      "estimated_cost_dkk": 31.802820833333303,
      "underutilized_cost_dkk": 0.0,
      "gpu_hours": 0.0,
      "jobs": 178,
      "jobs_with_measured_cpu": 0,
      "jobs_with_measured_memory": 0,
      "cpu_hours_allocated": 483.1097222222224,
      "measured_cpu_hours": 0.0,
      "requested_mem_gb_hours": 1263.2783333333327,
      "measured_mem_gb_max_sum": 0.0
    },
    {
      "report_date": "2025-08-20",
      "avg_cpu_efficiency": null,
      "avg_memory_efficiency": null,
      "estimated_cost_dkk": 32.13899722222222,
      "underutilized_cost_dkk": 0.0,
      "gpu_hours": 0.0,
      "jobs": 58,
      "jobs_with_measured_cpu": 0,
      "jobs_with_measured_memory": 0,
      "cpu_hours_allocated": 448.8061111111111,
      "measured_cpu_hours": 0.0,
      "requested_mem_gb_hours": 728.7644444444444,
      "measured_mem_gb_max_sum": 0.0
    },
    {
      "report_date": "2025-08-21",
      "avg_cpu_efficiency": null,
      "avg_memory_efficiency": null,
      "estimated_cost_dkk": 20.12569722222222,
      "underutilized_cost_dkk": 0.0,
      "gpu_hours": 0.0,
      "jobs": 54,
      "jobs_with_measured_cpu": 0,
      "jobs_with_measured_memory": 0,
      "cpu_hours_allocated": 226.37944444444443,
      "measured_cpu_hours": 0.0,
      "requested_mem_gb_hours": 1214.46,
      "measured_mem_gb_max_sum": 0.0
    },
    {
      "report_date": "2025-08-22",
      "avg_cpu_efficiency": null,
      "avg_memory_efficiency": null,
      "estimated_cost_dkk": 56.82655694444445,
      "underutilized_cost_dkk": 0.0,
      "gpu_hours": 0.0,
      "jobs": 43,
      "jobs_with_measured_cpu": 0,
      "jobs_with_measured_memory": 0,
      "cpu_hours_allocated": 855.2380555555555,
      "measured_cpu_hours": 0.0,
      "requested_mem_gb_hours": 886.2161111111112,
      "measured_mem_gb_max_sum": 0.0
    },
    {
      "report_date": "2025-08-23",
      "avg_cpu_efficiency": null,
      "avg_memory_efficiency": null,
      "estimated_cost_dkk": 41.19385833333331,
      "underutilized_cost_dkk": 0.0,
      "gpu_hours": 0.0,
      "jobs": 178,
      "jobs_with_measured_cpu": 0,
      "jobs_with_measured_memory": 0,
      "cpu_hours_allocated": 633.751666666666,
      "measured_cpu_hours": 0.0,
      "requested_mem_gb_hours": 984.5733333333338,
      "measured_mem_gb_max_sum": 0.0
    },
    {
      "report_date": "2025-08-25",
      "avg_cpu_efficiency": null,
      "avg_memory_efficiency": null,
      "estimated_cost_dkk": 8.011936111111112,
      "underutilized_cost_dkk": 0.0,
      "gpu_hours": 0.0,
      "jobs": 13,
      "jobs_with_measured_cpu": 0,
      "jobs_with_measured_memory": 0,
      "cpu_hours_allocated": 114.57833333333333,
      "measured_cpu_hours": 0.0,
      "requested_mem_gb_hours": 371.1255555555556,
      "measured_mem_gb_max_sum": 0.0
    },
    {
      "report_date": "2025-08-27",
      "avg_cpu_efficiency": null,
      "avg_memory_efficiency": null,
      "estimated_cost_dkk": 143.5529333333333,
      "underutilized_cost_dkk": 0.0,
      "gpu_hours": 0.0,
      "jobs": 150,
      "jobs_with_measured_cpu": 0,
      "jobs_with_measured_memory": 0,
      "cpu_hours_allocated": 2208.5066666666667,
      "measured_cpu_hours": 0.0,
      "requested_mem_gb_hours": 2208.5066666666667,
      "measured_mem_gb_max_sum": 0.0
    },
    {
      "report_date": "2025-08-28",
      "avg_cpu_efficiency": null,
      "avg_memory_efficiency": null,
      "estimated_cost_dkk": 84.89317777777778,
      "underutilized_cost_dkk": 0.0,
      "gpu_hours": 0.0,
      "jobs": 28,
      "jobs_with_measured_cpu": 0,
      "jobs_with_measured_memory": 0,
      "cpu_hours_allocated": 1306.0477777777778,
      "measured_cpu_hours": 0.0,
      "requested_mem_gb_hours": 3445.882222222223,
      "measured_mem_gb_max_sum": 0.0
    },
    {
      "report_date": "2025-08-29",
      "avg_cpu_efficiency": null,
      "avg_memory_efficiency": null,
      "estimated_cost_dkk": 25.98873333333333,
      "underutilized_cost_dkk": 0.0,
      "gpu_hours": 0.0,
      "jobs": 2,
      "jobs_with_measured_cpu": 0,
      "jobs_with_measured_memory": 0,
      "cpu_hours_allocated": 399.8266666666666,
      "measured_cpu_hours": 0.0,
      "requested_mem_gb_hours": 1032.8855555555554,
      "measured_mem_gb_max_sum": 0.0
    },
    {
      "report_date": "2025-09-01",
      "avg_cpu_efficiency": null,
      "avg_memory_efficiency": null,
      "estimated_cost_dkk": 0.5228166666666667,
      "underutilized_cost_dkk": 0.0,
      "gpu_hours": 0.0,
      "jobs": 1,
      "jobs_with_measured_cpu": 0,
      "jobs_with_measured_memory": 0,
      "cpu_hours_allocated": 8.043333333333333,
      "measured_cpu_hours": 0.0,
      "requested_mem_gb_hours": 21.448888888888888,
      "measured_mem_gb_max_sum": 0.0
    },
    {
      "report_date": "2025-09-09",
      "avg_cpu_efficiency": null,
      "avg_memory_efficiency": null,
      "estimated_cost_dkk": 1.5363833333333334,
      "underutilized_cost_dkk": 0.0,
      "gpu_hours": 0.0,
      "jobs": 1,
      "jobs_with_measured_cpu": 0,
      "jobs_with_measured_memory": 0,
      "cpu_hours_allocated": 23.636666666666667,
      "measured_cpu_hours": 0.0,
      "requested_mem_gb_hours": 63.03111111111111,
      "measured_mem_gb_max_sum": 0.0
    },
    {
      "report_date": "2025-09-21",
      "avg_cpu_efficiency": null,
      "avg_memory_efficiency": null,
      "estimated_cost_dkk": 0.010833333333333334,
      "underutilized_cost_dkk": 0.0,
      "gpu_hours": 0.0,
      "jobs": 4,
      "jobs_with_measured_cpu": 0,
      "jobs_with_measured_memory": 0,
      "cpu_hours_allocated": 0.16666666666666666,
      "measured_cpu_hours": 0.0,
      "requested_mem_gb_hours": 0.08333333333333333,
      "measured_mem_gb_max_sum": 0.0
    },
    {
      "report_date": "2025-09-22",
      "avg_cpu_efficiency": null,
      "avg_memory_efficiency": null,
      "estimated_cost_dkk": 1.2081694444444446,
      "underutilized_cost_dkk": 0.0,
      "gpu_hours": 0.0,
      "jobs": 31,
      "jobs_with_measured_cpu": 0,
      "jobs_with_measured_memory": 0,
      "cpu_hours_allocated": 18.367500000000007,
      "measured_cpu_hours": 0.0,
      "requested_mem_gb_hours": 49.805,
      "measured_mem_gb_max_sum": 0.0
    },
    {
      "report_date": "2025-09-23",
      "avg_cpu_efficiency": null,
      "avg_memory_efficiency": null,
      "estimated_cost_dkk": 3.7471777777777784,
      "underutilized_cost_dkk": 0.0,
      "gpu_hours": 0.0,
      "jobs": 8,
      "jobs_with_measured_cpu": 0,
      "jobs_with_measured_memory": 0,
      "cpu_hours_allocated": 11.801666666666666,
      "measured_cpu_hours": 0.0,
      "requested_mem_gb_hours": 229.46194444444447,
      "measured_mem_gb_max_sum": 0.0
    },
    {
      "report_date": "2025-09-24",
      "avg_cpu_efficiency": null,
      "avg_memory_efficiency": null,
      "estimated_cost_dkk": 0.11113194444444445,
      "underutilized_cost_dkk": 0.0,
      "gpu_hours": 0.0,
      "jobs": 12,
      "jobs_with_measured_cpu": 0,
      "jobs_with_measured_memory": 0,
      "cpu_hours_allocated": 1.7097222222222221,
      "measured_cpu_hours": 0.0,
      "requested_mem_gb_hours": 4.844444444444445,
      "measured_mem_gb_max_sum": 0.0
    },
    {
      "report_date": "2025-09-25",
      "avg_cpu_efficiency": null,
      "avg_memory_efficiency": null,
      "estimated_cost_dkk": 0.32702222222222227,
      "underutilized_cost_dkk": 0.0,
      "gpu_hours": 0.0,
      "jobs": 9,
      "jobs_with_measured_cpu": 0,
      "jobs_with_measured_memory": 0,
      "cpu_hours_allocated": 2.675277777777778,
      "measured_cpu_hours": 0.0,
      "requested_mem_gb_hours": 20.083333333333336,
      "measured_mem_gb_max_sum": 0.0
    },
    {
      "report_date": "2025-09-26",
      "avg_cpu_efficiency": null,
      "avg_memory_efficiency": null,
      "estimated_cost_dkk": 2.416925694444445,
      "underutilized_cost_dkk": 0.0,
      "gpu_hours": 0.0,
      "jobs": 40,
      "jobs_with_measured_cpu": 0,
      "jobs_with_measured_memory": 0,
      "cpu_hours_allocated": 29.750555555555557,
      "measured_cpu_hours": 0.0,
      "requested_mem_gb_hours": 148.73388888888888,
      "measured_mem_gb_max_sum": 0.0
    },
    {
      "report_date": "2025-10-03",
      "avg_cpu_efficiency": null,
      "avg_memory_efficiency": null,
      "estimated_cost_dkk": 2.3407312499999997,
      "underutilized_cost_dkk": 0.0,
      "gpu_hours": 0.0,
      "jobs": 1,
      "jobs_with_measured_cpu": 0,
      "jobs_with_measured_memory": 0,
      "cpu_hours_allocated": 32.01,
      "measured_cpu_hours": 0.0,
      "requested_mem_gb_hours": 144.045,
      "measured_mem_gb_max_sum": 0.0
    },
    {
      "report_date": "2025-10-06",
      "avg_cpu_efficiency": null,
      "avg_memory_efficiency": null,
      "estimated_cost_dkk": 10.599333333333334,
      "underutilized_cost_dkk": 0.0,
      "gpu_hours": 0.0,
      "jobs": 32,
      "jobs_with_measured_cpu": 0,
      "jobs_with_measured_memory": 0,
      "cpu_hours_allocated": 163.0666666666667,
      "measured_cpu_hours": 0.0,
      "requested_mem_gb_hours": 164.05999999999997,
      "measured_mem_gb_max_sum": 0.0
    },
    {
      "report_date": "2025-10-07",
      "avg_cpu_efficiency": null,
      "avg_memory_efficiency": null,
      "estimated_cost_dkk": 1.3361111111111112,
      "underutilized_cost_dkk": 0.0,
      "gpu_hours": 0.0,
      "jobs": 42,
      "jobs_with_measured_cpu": 0,
      "jobs_with_measured_memory": 0,
      "cpu_hours_allocated": 20.555555555555554,
      "measured_cpu_hours": 0.0,
      "requested_mem_gb_hours": 41.11111111111111,
      "measured_mem_gb_max_sum": 0.0
    },
    {
      "report_date": "2025-10-08",
      "avg_cpu_efficiency": null,
      "avg_memory_efficiency": null,
      "estimated_cost_dkk": 5.06321111111111,
      "underutilized_cost_dkk": 0.0,
      "gpu_hours": 0.0,
      "jobs": 65,
      "jobs_with_measured_cpu": 0,
      "jobs_with_measured_memory": 0,
      "cpu_hours_allocated": 77.89555555555556,
      "measured_cpu_hours": 0.0,
      "requested_mem_gb_hours": 155.79111111111112,
      "measured_mem_gb_max_sum": 0.0
    },
    {
      "report_date": "2025-10-16",
      "avg_cpu_efficiency": null,
      "avg_memory_efficiency": null,
      "estimated_cost_dkk": 0.9344111111111112,
      "underutilized_cost_dkk": 0.0,
      "gpu_hours": 0.0,
      "jobs": 1,
      "jobs_with_measured_cpu": 0,
      "jobs_with_measured_memory": 0,
      "cpu_hours_allocated": 14.375555555555556,
      "measured_cpu_hours": 0.0,
      "requested_mem_gb_hours": 57.50222222222222,
      "measured_mem_gb_max_sum": 0.0
    },
    {
      "report_date": "2026-01-27",
      "avg_cpu_efficiency": null,
      "avg_memory_efficiency": null,
      "estimated_cost_dkk": 11.871997222222221,
      "underutilized_cost_dkk": 0.0,
      "gpu_hours": 0.0,
      "jobs": 15,
      "jobs_with_measured_cpu": 0,
      "jobs_with_measured_memory": 0,
      "cpu_hours_allocated": 42.54833333333333,
      "measured_cpu_hours": 0.0,
      "requested_mem_gb_hours": 730.5844444444444,
      "measured_mem_gb_max_sum": 0.0
    },
    {
      "report_date": "2026-01-28",
      "avg_cpu_efficiency": null,
      "avg_memory_efficiency": null,
      "estimated_cost_dkk": 3.8933555555555555,
      "underutilized_cost_dkk": 0.0,
      "gpu_hours": 0.0,
      "jobs": 1,
      "jobs_with_measured_cpu": 0,
      "jobs_with_measured_memory": 0,
      "cpu_hours_allocated": 14.974444444444444,
      "measured_cpu_hours": 0.0,
      "requested_mem_gb_hours": 239.5911111111111,
      "measured_mem_gb_max_sum": 0.0
    },
    {
      "report_date": "2026-01-30",
      "avg_cpu_efficiency": null,
      "avg_memory_efficiency": null,
      "estimated_cost_dkk": 0.0,
      "underutilized_cost_dkk": 0.0,
      "gpu_hours": 0.0,
      "jobs": 1,
      "jobs_with_measured_cpu": 0,
      "jobs_with_measured_memory": 0,
      "cpu_hours_allocated": 0.0,
      "measured_cpu_hours": 0.0,
      "requested_mem_gb_hours": 0.0,
      "measured_mem_gb_max_sum": 0.0
    },
    {
      "report_date": "2026-02-05",
      "avg_cpu_efficiency": null,
      "avg_memory_efficiency": null,
      "estimated_cost_dkk": 1.3262888888888889,
      "underutilized_cost_dkk": 0.0,
      "gpu_hours": 0.0,
      "jobs": 1,
      "jobs_with_measured_cpu": 0,
      "jobs_with_measured_memory": 0,
      "cpu_hours_allocated": 20.404444444444444,
      "measured_cpu_hours": 0.0,
      "requested_mem_gb_hours": 81.61777777777777,
      "measured_mem_gb_max_sum": 0.0
    },
    {
      "report_date": "2026-02-06",
      "avg_cpu_efficiency": null,
      "avg_memory_efficiency": null,
      "estimated_cost_dkk": 7.325644444444444,
      "underutilized_cost_dkk": 0.0,
      "gpu_hours": 0.0,
      "jobs": 1,
      "jobs_with_measured_cpu": 0,
      "jobs_with_measured_memory": 0,
      "cpu_hours_allocated": 84.52666666666667,
      "measured_cpu_hours": 0.0,
      "requested_mem_gb_hours": 450.8088888888889,
      "measured_mem_gb_max_sum": 0.0
    },
    {
      "report_date": "2026-02-13",
      "avg_cpu_efficiency": null,
      "avg_memory_efficiency": null,
      "estimated_cost_dkk": 3.0486444444444443,
      "underutilized_cost_dkk": 0.0,
      "gpu_hours": 0.0,
      "jobs": 1,
      "jobs_with_measured_cpu": 0,
      "jobs_with_measured_memory": 0,
      "cpu_hours_allocated": 46.90222222222222,
      "measured_cpu_hours": 0.0,
      "requested_mem_gb_hours": 187.60888888888888,
      "measured_mem_gb_max_sum": 0.0
    },
    {
      "report_date": "2026-02-23",
      "avg_cpu_efficiency": null,
      "avg_memory_efficiency": null,
      "estimated_cost_dkk": 0.04448888888888888,
      "underutilized_cost_dkk": 0.0,
      "gpu_hours": 0.0,
      "jobs": 20,
      "jobs_with_measured_cpu": 0,
      "jobs_with_measured_memory": 0,
      "cpu_hours_allocated": 0.6844444444444444,
      "measured_cpu_hours": 0.0,
      "requested_mem_gb_hours": 2.6555555555555563,
      "measured_mem_gb_max_sum": 0.0
    }
  ],
  "recommendations": [],
  "top_inefficient_jobs": [],
  "leaf": {
    "version": "2.0",
    "window_days": 180,
    "leaf_index": null,
    "leaf_index_components": [],
    "confidence": "very_low",
    "measurement_coverage": {
      "jobs_measured": 0,
      "jobs_excluded": 40,
      "jobs_measured_pct": 0.0,
      "cpu_hours_measured_pct": 0.0,
      "memory_measured_pct": 0.0
    },
    "percentile": null
  },
  "public_user_id": "usr_2e80908ce0eb",
  "display_pseudonym": "Silver Raven",
  "personal_route_token": "u_3661a3a17ebc4834eb6b87b47108f767",
  "username": "skl448",
  "percentile_position": {
    "overall": null,
    "cpu": null,
    "memory": null,
    "savings": null
  },
  "peer_comparisons": []
}
