{
  "schema_version": "analytics-v1",
  "generated_at": "2026-07-09T22:25:21Z",
  "all_time_summary": {
    "jobs": 317,
    "completed_jobs": 175,
    "failed_jobs": 142,
    "cpu_hours_allocated": 809.479722,
    "measured_cpu_hours": 0.121111,
    "avg_cpu_efficiency": 0.539504,
    "jobs_with_measured_cpu": 3,
    "requested_mem_gb_hours": 11133.023333,
    "measured_mem_gb_max_sum": 6.286944,
    "avg_memory_efficiency": 0.523912,
    "jobs_with_measured_memory": 3,
    "estimated_cost_dkk": 181.857208,
    "underutilized_cost_dkk": 0.050646,
    "gpu_hours": 0.0,
    "cpu_cost_dkk": 52.616182,
    "mem_cost_dkk": 180.911629,
    "gpu_cost_dkk": 0.0,
    "cost_bearer": "memory",
    "cost_bearer_cost_dkk": 180.911629,
    "cost_bearer_efficiency": 0.523912,
    "cost_bearer_waste_dkk": 0.050646,
    "leaf_index": 53,
    "leaf_index_components": [
      {
        "id": "cpu",
        "label": "CPU efficiency",
        "value": 0.5395,
        "weight": 0.6,
        "contribution": 0.3237
      },
      {
        "id": "memory",
        "label": "Memory efficiency",
        "value": 0.5239,
        "weight": 0.4,
        "contribution": 0.2096
      }
    ]
  },
  "rolling_summaries": {
    "7d": {
      "jobs": 0,
      "completed_jobs": 0,
      "failed_jobs": 0,
      "cpu_hours_allocated": 0.0,
      "measured_cpu_hours": 0.0,
      "avg_cpu_efficiency": null,
      "jobs_with_measured_cpu": 0,
      "requested_mem_gb_hours": 0.0,
      "measured_mem_gb_max_sum": 0.0,
      "avg_memory_efficiency": null,
      "jobs_with_measured_memory": 0,
      "estimated_cost_dkk": 0.0,
      "underutilized_cost_dkk": 0.0,
      "gpu_hours": 0.0,
      "cpu_cost_dkk": 0.0,
      "mem_cost_dkk": 0.0,
      "gpu_cost_dkk": 0.0,
      "cost_bearer": "cpu",
      "cost_bearer_cost_dkk": 0.0,
      "cost_bearer_efficiency": null,
      "cost_bearer_waste_dkk": 0.0,
      "leaf_index": null,
      "leaf_index_components": []
    },
    "30d": {
      "jobs": 0,
      "completed_jobs": 0,
      "failed_jobs": 0,
      "cpu_hours_allocated": 0.0,
      "measured_cpu_hours": 0.0,
      "avg_cpu_efficiency": null,
      "jobs_with_measured_cpu": 0,
      "requested_mem_gb_hours": 0.0,
      "measured_mem_gb_max_sum": 0.0,
      "avg_memory_efficiency": null,
      "jobs_with_measured_memory": 0,
      "estimated_cost_dkk": 0.0,
      "underutilized_cost_dkk": 0.0,
      "gpu_hours": 0.0,
      "cpu_cost_dkk": 0.0,
      "mem_cost_dkk": 0.0,
      "gpu_cost_dkk": 0.0,
      "cost_bearer": "cpu",
      "cost_bearer_cost_dkk": 0.0,
      "cost_bearer_efficiency": null,
      "cost_bearer_waste_dkk": 0.0,
      "leaf_index": null,
      "leaf_index_components": []
    },
    "90d": {
      "jobs": 0,
      "completed_jobs": 0,
      "failed_jobs": 0,
      "cpu_hours_allocated": 0.0,
      "measured_cpu_hours": 0.0,
      "avg_cpu_efficiency": null,
      "jobs_with_measured_cpu": 0,
      "requested_mem_gb_hours": 0.0,
      "measured_mem_gb_max_sum": 0.0,
      "avg_memory_efficiency": null,
      "jobs_with_measured_memory": 0,
      "estimated_cost_dkk": 0.0,
      "underutilized_cost_dkk": 0.0,
      "gpu_hours": 0.0,
      "cpu_cost_dkk": 0.0,
      "mem_cost_dkk": 0.0,
      "gpu_cost_dkk": 0.0,
      "cost_bearer": "cpu",
      "cost_bearer_cost_dkk": 0.0,
      "cost_bearer_efficiency": null,
      "cost_bearer_waste_dkk": 0.0,
      "leaf_index": null,
      "leaf_index_components": []
    },
    "180d": {
      "jobs": 116,
      "completed_jobs": 56,
      "failed_jobs": 60,
      "cpu_hours_allocated": 73.131667,
      "measured_cpu_hours": 0.121111,
      "avg_cpu_efficiency": 0.539504,
      "jobs_with_measured_cpu": 3,
      "requested_mem_gb_hours": 696.906667,
      "measured_mem_gb_max_sum": 6.286944,
      "avg_memory_efficiency": 0.523912,
      "jobs_with_measured_memory": 3,
      "estimated_cost_dkk": 11.335819,
      "underutilized_cost_dkk": 0.050646,
      "gpu_hours": 0.0,
      "cpu_cost_dkk": 4.753558,
      "mem_cost_dkk": 11.324733,
      "gpu_cost_dkk": 0.0,
      "cost_bearer": "memory",
      "cost_bearer_cost_dkk": 11.324733,
      "cost_bearer_efficiency": 0.523912,
      "cost_bearer_waste_dkk": 0.050646,
      "leaf_index": 53,
      "leaf_index_components": [
        {
          "id": "cpu",
          "label": "CPU efficiency",
          "value": 0.5395,
          "weight": 0.6,
          "contribution": 0.3237
        },
        {
          "id": "memory",
          "label": "Memory efficiency",
          "value": 0.5239,
          "weight": 0.4,
          "contribution": 0.2096
        }
      ]
    }
  },
  "daily_trends": [
    {
      "report_date": "2024-07-17",
      "avg_cpu_efficiency": null,
      "avg_memory_efficiency": null,
      "estimated_cost_dkk": 0.18763333333333332,
      "underutilized_cost_dkk": 0.0,
      "gpu_hours": 0.0,
      "jobs": 13,
      "jobs_with_measured_cpu": 0,
      "jobs_with_measured_memory": 0,
      "cpu_hours_allocated": 2.8866666666666667,
      "measured_cpu_hours": 0.0,
      "requested_mem_gb_hours": 8.483333333333333,
      "measured_mem_gb_max_sum": 0.0
    },
    {
      "report_date": "2025-01-23",
      "avg_cpu_efficiency": null,
      "avg_memory_efficiency": null,
      "estimated_cost_dkk": 0.32498194444444445,
      "underutilized_cost_dkk": 0.0,
      "gpu_hours": 0.0,
      "jobs": 3,
      "jobs_with_measured_cpu": 0,
      "jobs_with_measured_memory": 0,
      "cpu_hours_allocated": 4.066388888888889,
      "measured_cpu_hours": 0.0,
      "requested_mem_gb_hours": 19.33277777777778,
      "measured_mem_gb_max_sum": 0.0
    },
    {
      "report_date": "2025-02-04",
      "avg_cpu_efficiency": null,
      "avg_memory_efficiency": null,
      "estimated_cost_dkk": 0.17685416666666667,
      "underutilized_cost_dkk": 0.0,
      "gpu_hours": 0.0,
      "jobs": 9,
      "jobs_with_measured_cpu": 0,
      "jobs_with_measured_memory": 0,
      "cpu_hours_allocated": 0.5441666666666666,
      "measured_cpu_hours": 0.0,
      "requested_mem_gb_hours": 10.883333333333333,
      "measured_mem_gb_max_sum": 0.0
    },
    {
      "report_date": "2025-02-05",
      "avg_cpu_efficiency": null,
      "avg_memory_efficiency": null,
      "estimated_cost_dkk": 0.008125,
      "underutilized_cost_dkk": 0.0,
      "gpu_hours": 0.0,
      "jobs": 1,
      "jobs_with_measured_cpu": 0,
      "jobs_with_measured_memory": 0,
      "cpu_hours_allocated": 0.05,
      "measured_cpu_hours": 0.0,
      "requested_mem_gb_hours": 0.5,
      "measured_mem_gb_max_sum": 0.0
    },
    {
      "report_date": "2025-02-06",
      "avg_cpu_efficiency": null,
      "avg_memory_efficiency": null,
      "estimated_cost_dkk": 0.03990277777777779,
      "underutilized_cost_dkk": 0.0,
      "gpu_hours": 0.0,
      "jobs": 11,
      "jobs_with_measured_cpu": 0,
      "jobs_with_measured_memory": 0,
      "cpu_hours_allocated": 0.12277777777777778,
      "measured_cpu_hours": 0.0,
      "requested_mem_gb_hours": 2.4555555555555553,
      "measured_mem_gb_max_sum": 0.0
    },
    {
      "report_date": "2025-02-07",
      "avg_cpu_efficiency": null,
      "avg_memory_efficiency": null,
      "estimated_cost_dkk": 0.29430555555555554,
      "underutilized_cost_dkk": 0.0,
      "gpu_hours": 0.0,
      "jobs": 2,
      "jobs_with_measured_cpu": 0,
      "jobs_with_measured_memory": 0,
      "cpu_hours_allocated": 0.9055555555555556,
      "measured_cpu_hours": 0.0,
      "requested_mem_gb_hours": 18.11111111111111,
      "measured_mem_gb_max_sum": 0.0
    },
    {
      "report_date": "2025-02-08",
      "avg_cpu_efficiency": null,
      "avg_memory_efficiency": null,
      "estimated_cost_dkk": 27.031694444444447,
      "underutilized_cost_dkk": 0.0,
      "gpu_hours": 0.0,
      "jobs": 1,
      "jobs_with_measured_cpu": 0,
      "jobs_with_measured_memory": 0,
      "cpu_hours_allocated": 166.3488888888889,
      "measured_cpu_hours": 0.0,
      "requested_mem_gb_hours": 1663.488888888889,
      "measured_mem_gb_max_sum": 0.0
    },
    {
      "report_date": "2025-02-11",
      "avg_cpu_efficiency": null,
      "avg_memory_efficiency": null,
      "estimated_cost_dkk": 78.00306944444445,
      "underutilized_cost_dkk": 0.0,
      "gpu_hours": 0.0,
      "jobs": 1,
      "jobs_with_measured_cpu": 0,
      "jobs_with_measured_memory": 0,
      "cpu_hours_allocated": 240.00944444444445,
      "measured_cpu_hours": 0.0,
      "requested_mem_gb_hours": 4800.188888888889,
      "measured_mem_gb_max_sum": 0.0
    },
    {
      "report_date": "2025-02-12",
      "avg_cpu_efficiency": null,
      "avg_memory_efficiency": null,
      "estimated_cost_dkk": 0.04895763888888889,
      "underutilized_cost_dkk": 0.0,
      "gpu_hours": 0.0,
      "jobs": 2,
      "jobs_with_measured_cpu": 0,
      "jobs_with_measured_memory": 0,
      "cpu_hours_allocated": 0.6027777777777777,
      "measured_cpu_hours": 0.0,
      "requested_mem_gb_hours": 3.0127777777777776,
      "measured_mem_gb_max_sum": 0.0
    },
    {
      "report_date": "2025-02-13",
      "avg_cpu_efficiency": null,
      "avg_memory_efficiency": null,
      "estimated_cost_dkk": 0.0021666666666666666,
      "underutilized_cost_dkk": 0.0,
      "gpu_hours": 0.0,
      "jobs": 1,
      "jobs_with_measured_cpu": 0,
      "jobs_with_measured_memory": 0,
      "cpu_hours_allocated": 0.0033333333333333335,
      "measured_cpu_hours": 0.0,
      "requested_mem_gb_hours": 0.13333333333333333,
      "measured_mem_gb_max_sum": 0.0
    },
    {
      "report_date": "2025-02-16",
      "avg_cpu_efficiency": null,
      "avg_memory_efficiency": null,
      "estimated_cost_dkk": 0.39274444444444445,
      "underutilized_cost_dkk": 0.0,
      "gpu_hours": 0.0,
      "jobs": 4,
      "jobs_with_measured_cpu": 0,
      "jobs_with_measured_memory": 0,
      "cpu_hours_allocated": 3.0077777777777777,
      "measured_cpu_hours": 0.0,
      "requested_mem_gb_hours": 24.168888888888887,
      "measured_mem_gb_max_sum": 0.0
    },
    {
      "report_date": "2025-02-17",
      "avg_cpu_efficiency": null,
      "avg_memory_efficiency": null,
      "estimated_cost_dkk": 40.26466527777777,
      "underutilized_cost_dkk": 0.0,
      "gpu_hours": 0.0,
      "jobs": 51,
      "jobs_with_measured_cpu": 0,
      "jobs_with_measured_memory": 0,
      "cpu_hours_allocated": 115.4408333333333,
      "measured_cpu_hours": 0.0,
      "requested_mem_gb_hours": 2475.173888888889,
      "measured_mem_gb_max_sum": 0.0
    },
    {
      "report_date": "2025-02-18",
      "avg_cpu_efficiency": null,
      "avg_memory_efficiency": null,
      "estimated_cost_dkk": 14.246555555555556,
      "underutilized_cost_dkk": 0.0,
      "gpu_hours": 0.0,
      "jobs": 1,
      "jobs_with_measured_cpu": 0,
      "jobs_with_measured_memory": 0,
      "cpu_hours_allocated": 109.58888888888889,
      "measured_cpu_hours": 0.0,
      "requested_mem_gb_hours": 876.7111111111111,
      "measured_mem_gb_max_sum": 0.0
    },
    {
      "report_date": "2025-02-19",
      "avg_cpu_efficiency": null,
      "avg_memory_efficiency": null,
      "estimated_cost_dkk": 0.39108333333333334,
      "underutilized_cost_dkk": 0.0,
      "gpu_hours": 0.0,
      "jobs": 5,
      "jobs_with_measured_cpu": 0,
      "jobs_with_measured_memory": 0,
      "cpu_hours_allocated": 6.01,
      "measured_cpu_hours": 0.0,
      "requested_mem_gb_hours": 12.066666666666666,
      "measured_mem_gb_max_sum": 0.0
    },
    {
      "report_date": "2025-02-20",
      "avg_cpu_efficiency": null,
      "avg_memory_efficiency": null,
      "estimated_cost_dkk": 6.628375,
      "underutilized_cost_dkk": 0.0,
      "gpu_hours": 0.0,
      "jobs": 3,
      "jobs_with_measured_cpu": 0,
      "jobs_with_measured_memory": 0,
      "cpu_hours_allocated": 54.88055555555556,
      "measured_cpu_hours": 0.0,
      "requested_mem_gb_hours": 407.9,
      "measured_mem_gb_max_sum": 0.0
    },
    {
      "report_date": "2025-02-25",
      "avg_cpu_efficiency": null,
      "avg_memory_efficiency": null,
      "estimated_cost_dkk": 0.2761416666666667,
      "underutilized_cost_dkk": 0.0,
      "gpu_hours": 0.0,
      "jobs": 16,
      "jobs_with_measured_cpu": 0,
      "jobs_with_measured_memory": 0,
      "cpu_hours_allocated": 2.9130555555555557,
      "measured_cpu_hours": 0.0,
      "requested_mem_gb_hours": 13.837777777777779,
      "measured_mem_gb_max_sum": 0.0
    },
    {
      "report_date": "2025-02-26",
      "avg_cpu_efficiency": null,
      "avg_memory_efficiency": null,
      "estimated_cost_dkk": 0.13216666666666665,
      "underutilized_cost_dkk": 0.0,
      "gpu_hours": 0.0,
      "jobs": 5,
      "jobs_with_measured_cpu": 0,
      "jobs_with_measured_memory": 0,
      "cpu_hours_allocated": 2.033333333333333,
      "measured_cpu_hours": 0.0,
      "requested_mem_gb_hours": 4.066666666666666,
      "measured_mem_gb_max_sum": 0.0
    },
    {
      "report_date": "2025-02-28",
      "avg_cpu_efficiency": null,
      "avg_memory_efficiency": null,
      "estimated_cost_dkk": 0.00014444444444444444,
      "underutilized_cost_dkk": 0.0,
      "gpu_hours": 0.0,
      "jobs": 1,
      "jobs_with_measured_cpu": 0,
      "jobs_with_measured_memory": 0,
      "cpu_hours_allocated": 0.0022222222222222222,
      "measured_cpu_hours": 0.0,
      "requested_mem_gb_hours": 0.0044444444444444444,
      "measured_mem_gb_max_sum": 0.0
    },
    {
      "report_date": "2025-03-04",
      "avg_cpu_efficiency": null,
      "avg_memory_efficiency": null,
      "estimated_cost_dkk": 0.3958319444444445,
      "underutilized_cost_dkk": 0.0,
      "gpu_hours": 0.0,
      "jobs": 22,
      "jobs_with_measured_cpu": 0,
      "jobs_with_measured_memory": 0,
      "cpu_hours_allocated": 6.089722222222224,
      "measured_cpu_hours": 0.0,
      "requested_mem_gb_hours": 21.201666666666664,
      "measured_mem_gb_max_sum": 0.0
    },
    {
      "report_date": "2025-03-05",
      "avg_cpu_efficiency": null,
      "avg_memory_efficiency": null,
      "estimated_cost_dkk": 0.5353111111111112,
      "underutilized_cost_dkk": 0.0,
      "gpu_hours": 0.0,
      "jobs": 23,
      "jobs_with_measured_cpu": 0,
      "jobs_with_measured_memory": 0,
      "cpu_hours_allocated": 8.235555555555557,
      "measured_cpu_hours": 0.0,
      "requested_mem_gb_hours": 25.54222222222223,
      "measured_mem_gb_max_sum": 0.0
    },
    {
      "report_date": "2025-03-06",
      "avg_cpu_efficiency": null,
      "avg_memory_efficiency": null,
      "estimated_cost_dkk": 0.23977777777777778,
      "underutilized_cost_dkk": 0.0,
      "gpu_hours": 0.0,
      "jobs": 6,
      "jobs_with_measured_cpu": 0,
      "jobs_with_measured_memory": 0,
      "cpu_hours_allocated": 3.070555555555556,
      "measured_cpu_hours": 0.0,
      "requested_mem_gb_hours": 11.248888888888889,
      "measured_mem_gb_max_sum": 0.0
    },
    {
      "report_date": "2025-03-07",
      "avg_cpu_efficiency": null,
      "avg_memory_efficiency": null,
      "estimated_cost_dkk": 0.5473000000000001,
      "underutilized_cost_dkk": 0.0,
      "gpu_hours": 0.0,
      "jobs": 11,
      "jobs_with_measured_cpu": 0,
      "jobs_with_measured_memory": 0,
      "cpu_hours_allocated": 8.42,
      "measured_cpu_hours": 0.0,
      "requested_mem_gb_hours": 16.84,
      "measured_mem_gb_max_sum": 0.0
    },
    {
      "report_date": "2025-03-10",
      "avg_cpu_efficiency": null,
      "avg_memory_efficiency": null,
      "estimated_cost_dkk": 0.35359999999999997,
      "underutilized_cost_dkk": 0.0,
      "gpu_hours": 0.0,
      "jobs": 9,
      "jobs_with_measured_cpu": 0,
      "jobs_with_measured_memory": 0,
      "cpu_hours_allocated": 1.1155555555555556,
      "measured_cpu_hours": 0.0,
      "requested_mem_gb_hours": 20.764444444444443,
      "measured_mem_gb_max_sum": 0.0
    },
    {
      "report_date": "2026-01-26",
      "avg_cpu_efficiency": null,
      "avg_memory_efficiency": null,
      "estimated_cost_dkk": 3.7393958333333326,
      "underutilized_cost_dkk": 0.0,
      "gpu_hours": 0.0,
      "jobs": 54,
      "jobs_with_measured_cpu": 0,
      "jobs_with_measured_memory": 0,
      "cpu_hours_allocated": 7.6705555555555565,
      "measured_cpu_hours": 0.0,
      "requested_mem_gb_hours": 230.11666666666667,
      "measured_mem_gb_max_sum": 0.0
    },
    {
      "report_date": "2026-01-27",
      "avg_cpu_efficiency": null,
      "avg_memory_efficiency": null,
      "estimated_cost_dkk": 0.8528541666666667,
      "underutilized_cost_dkk": 0.0,
      "gpu_hours": 0.0,
      "jobs": 2,
      "jobs_with_measured_cpu": 0,
      "jobs_with_measured_memory": 0,
      "cpu_hours_allocated": 1.7494444444444444,
      "measured_cpu_hours": 0.0,
      "requested_mem_gb_hours": 52.483333333333334,
      "measured_mem_gb_max_sum": 0.0
    },
    {
      "report_date": "2026-02-18",
      "avg_cpu_efficiency": null,
      "avg_memory_efficiency": null,
      "estimated_cost_dkk": 0.023887500000000002,
      "underutilized_cost_dkk": 0.0,
      "gpu_hours": 0.0,
      "jobs": 14,
      "jobs_with_measured_cpu": 0,
      "jobs_with_measured_memory": 0,
      "cpu_hours_allocated": 0.025833333333333326,
      "measured_cpu_hours": 0.0,
      "requested_mem_gb_hours": 1.4699999999999998,
      "measured_mem_gb_max_sum": 0.0
    },
    {
      "report_date": "2026-02-19",
      "avg_cpu_efficiency": null,
      "avg_memory_efficiency": null,
      "estimated_cost_dkk": 0.05497916666666667,
      "underutilized_cost_dkk": 0.0,
      "gpu_hours": 0.0,
      "jobs": 1,
      "jobs_with_measured_cpu": 0,
      "jobs_with_measured_memory": 0,
      "cpu_hours_allocated": 0.04833333333333333,
      "measured_cpu_hours": 0.0,
      "requested_mem_gb_hours": 3.3833333333333333,
      "measured_mem_gb_max_sum": 0.0
    },
    {
      "report_date": "2026-02-20",
      "avg_cpu_efficiency": null,
      "avg_memory_efficiency": null,
      "estimated_cost_dkk": 0.09452986111111111,
      "underutilized_cost_dkk": 0.0,
      "gpu_hours": 0.0,
      "jobs": 7,
      "jobs_with_measured_cpu": 0,
      "jobs_with_measured_memory": 0,
      "cpu_hours_allocated": 0.17055555555555557,
      "measured_cpu_hours": 0.0,
      "requested_mem_gb_hours": 5.817222222222222,
      "measured_mem_gb_max_sum": 0.0
    },
    {
      "report_date": "2026-02-23",
      "avg_cpu_efficiency": null,
      "avg_memory_efficiency": null,
      "estimated_cost_dkk": 0.6879076388888888,
      "underutilized_cost_dkk": 0.0,
      "gpu_hours": 0.0,
      "jobs": 4,
      "jobs_with_measured_cpu": 0,
      "jobs_with_measured_memory": 0,
      "cpu_hours_allocated": 2.256944444444444,
      "measured_cpu_hours": 0.0,
      "requested_mem_gb_hours": 42.33277777777778,
      "measured_mem_gb_max_sum": 0.0
    },
    {
      "report_date": "2026-02-25",
      "avg_cpu_efficiency": null,
      "avg_memory_efficiency": null,
      "estimated_cost_dkk": 3.4007638888888887,
      "underutilized_cost_dkk": 0.0,
      "gpu_hours": 0.0,
      "jobs": 12,
      "jobs_with_measured_cpu": 0,
      "jobs_with_measured_memory": 0,
      "cpu_hours_allocated": 41.194166666666675,
      "measured_cpu_hours": 0.0,
      "requested_mem_gb_hours": 209.2777777777778,
      "measured_mem_gb_max_sum": 0.0
    },
    {
      "report_date": "2026-02-26",
      "avg_cpu_efficiency": null,
      "avg_memory_efficiency": null,
      "estimated_cost_dkk": 2.4008111111111115,
      "underutilized_cost_dkk": 0.0,
      "gpu_hours": 0.0,
      "jobs": 13,
      "jobs_with_measured_cpu": 0,
      "jobs_with_measured_memory": 0,
      "cpu_hours_allocated": 18.774444444444445,
      "measured_cpu_hours": 0.0,
      "requested_mem_gb_hours": 147.7422222222222,
      "measured_mem_gb_max_sum": 0.0
    },
    {
      "report_date": "2026-02-27",
      "avg_cpu_efficiency": null,
      "avg_memory_efficiency": null,
      "estimated_cost_dkk": 0.022172222222222225,
      "underutilized_cost_dkk": 0.0,
      "gpu_hours": 0.0,
      "jobs": 6,
      "jobs_with_measured_cpu": 0,
      "jobs_with_measured_memory": 0,
      "cpu_hours_allocated": 0.34111111111111114,
      "measured_cpu_hours": 0.0,
      "requested_mem_gb_hours": 0.6822222222222223,
      "measured_mem_gb_max_sum": 0.0
    },
    {
      "report_date": "2026-04-08",
      "avg_cpu_efficiency": 0.5395042263390707,
      "avg_memory_efficiency": 0.5239120324452718,
      "estimated_cost_dkk": 0.05851805555555556,
      "underutilized_cost_dkk": 0.050645833333333334,
      "gpu_hours": 0.0,
      "jobs": 3,
      "jobs_with_measured_cpu": 3,
      "jobs_with_measured_memory": 3,
      "cpu_hours_allocated": 0.9002777777777777,
      "measured_cpu_hours": 0.12111111111111111,
      "requested_mem_gb_hours": 3.601111111111111,
      "measured_mem_gb_max_sum": 6.286944389343262
    }
  ],
  "recommendations": [],
  "top_inefficient_jobs": [
    {
      "report_date": "2026-04-08",
      "partition_name": "cpuqueue",
      "state": "CANCELLED by 438576806",
      "alloc_cpus": 1,
      "elapsed_hours": 0.7555555555555555,
      "measured_cpu_efficiency": 0.0,
      "memory_efficiency": 0.9848594665527344,
      "gpu_count": 0,
      "estimated_cost_dkk": 0.04911111111111111,
      "underutilized_cost_dkk": 0.04911111111111111,
      "cpu_cost_dkk": 0.04911111111111111,
      "mem_cost_dkk": 0.04911111111111111,
      "gpu_cost_dkk": 0.0,
      "cost_bearer": "cpu",
      "cost_bearer_cost_dkk": 0.04911111111111111,
      "cost_bearer_efficiency": 0.0,
      "cost_bearer_waste_dkk": 0.04911111111111111
    },
    {
      "report_date": "2026-04-08",
      "partition_name": "cpuqueue",
      "state": "COMPLETED",
      "alloc_cpus": 1,
      "elapsed_hours": 0.049166666666666664,
      "measured_cpu_efficiency": 0.7231638418079096,
      "memory_efficiency": 0.19515156745910645,
      "gpu_count": 0,
      "estimated_cost_dkk": 0.003195833333333333,
      "underutilized_cost_dkk": 0.0008847222222222222,
      "cpu_cost_dkk": 0.003195833333333333,
      "mem_cost_dkk": 0.003195833333333333,
      "gpu_cost_dkk": 0.0,
      "cost_bearer": "cpu",
      "cost_bearer_cost_dkk": 0.003195833333333333,
      "cost_bearer_efficiency": 0.7231638418079096,
      "cost_bearer_waste_dkk": 0.0008847222222222222
    },
    {
      "report_date": "2026-04-08",
      "partition_name": "cpuqueue",
      "state": "COMPLETED",
      "alloc_cpus": 1,
      "elapsed_hours": 0.09555555555555556,
      "measured_cpu_efficiency": 0.8953488372093024,
      "memory_efficiency": 0.3917250633239746,
      "gpu_count": 0,
      "estimated_cost_dkk": 0.006211111111111112,
      "underutilized_cost_dkk": 0.0006499999999999999,
      "cpu_cost_dkk": 0.006211111111111112,
      "mem_cost_dkk": 0.006211111111111112,
      "gpu_cost_dkk": 0.0,
      "cost_bearer": "cpu",
      "cost_bearer_cost_dkk": 0.006211111111111112,
      "cost_bearer_efficiency": 0.8953488372093024,
      "cost_bearer_waste_dkk": 0.0006499999999999999
    }
  ],
  "leaf": {
    "version": "2.0",
    "window_days": 180,
    "leaf_index": 53,
    "leaf_index_components": [
      {
        "id": "cpu",
        "label": "CPU efficiency",
        "value": 0.5395,
        "weight": 0.6,
        "contribution": 0.3237
      },
      {
        "id": "memory",
        "label": "Memory efficiency",
        "value": 0.5239,
        "weight": 0.4,
        "contribution": 0.2096
      }
    ],
    "confidence": "very_low",
    "measurement_coverage": {
      "jobs_measured": 3,
      "jobs_excluded": 113,
      "jobs_measured_pct": 2.59,
      "cpu_hours_measured_pct": 0.17,
      "memory_measured_pct": 0.9
    },
    "percentile": 97.7
  },
  "public_user_id": "usr_f67f17e11b9a",
  "display_pseudonym": "Amber Condor",
  "personal_route_token": "u_9930289f7c63849c26f7f9237f14ba11",
  "username": "lgt297",
  "percentile_position": {
    "overall": null,
    "cpu": null,
    "memory": null,
    "savings": null
  },
  "peer_comparisons": []
}
