{
  "schema_version": "analytics-v1",
  "generated_at": "2026-06-30T18:36:31Z",
  "all_time_summary": {
    "jobs": 27,
    "completed_jobs": 10,
    "failed_jobs": 17,
    "cpu_hours_allocated": 40.444444,
    "measured_cpu_hours": 1.898889,
    "avg_cpu_efficiency": 0.07218,
    "jobs_with_measured_cpu": 18,
    "requested_mem_gb_hours": 397.74,
    "measured_mem_gb_max_sum": 20.954217,
    "avg_memory_efficiency": 0.010867,
    "jobs_with_measured_memory": 24,
    "estimated_cost_dkk": 6.463293,
    "underutilized_cost_dkk": 6.422709,
    "gpu_hours": 0.0,
    "cpu_cost_dkk": 2.628889,
    "mem_cost_dkk": 6.463275,
    "gpu_cost_dkk": 0.0,
    "cost_bearer": "memory",
    "cost_bearer_cost_dkk": 6.463275,
    "cost_bearer_efficiency": 0.010867,
    "cost_bearer_waste_dkk": 6.422709
  },
  "rolling_summaries": {
    "7d": {
      "jobs": 0,
      "completed_jobs": 0,
      "failed_jobs": 0,
      "cpu_hours_allocated": 0.0,
      "measured_cpu_hours": 0.0,
      "avg_cpu_efficiency": null,
      "jobs_with_measured_cpu": 0,
      "requested_mem_gb_hours": 0.0,
      "measured_mem_gb_max_sum": 0.0,
      "avg_memory_efficiency": null,
      "jobs_with_measured_memory": 0,
      "estimated_cost_dkk": 0.0,
      "underutilized_cost_dkk": 0.0,
      "gpu_hours": 0.0,
      "cpu_cost_dkk": 0.0,
      "mem_cost_dkk": 0.0,
      "gpu_cost_dkk": 0.0,
      "cost_bearer": "cpu",
      "cost_bearer_cost_dkk": 0.0,
      "cost_bearer_efficiency": null,
      "cost_bearer_waste_dkk": 0.0
    },
    "30d": {
      "jobs": 0,
      "completed_jobs": 0,
      "failed_jobs": 0,
      "cpu_hours_allocated": 0.0,
      "measured_cpu_hours": 0.0,
      "avg_cpu_efficiency": null,
      "jobs_with_measured_cpu": 0,
      "requested_mem_gb_hours": 0.0,
      "measured_mem_gb_max_sum": 0.0,
      "avg_memory_efficiency": null,
      "jobs_with_measured_memory": 0,
      "estimated_cost_dkk": 0.0,
      "underutilized_cost_dkk": 0.0,
      "gpu_hours": 0.0,
      "cpu_cost_dkk": 0.0,
      "mem_cost_dkk": 0.0,
      "gpu_cost_dkk": 0.0,
      "cost_bearer": "cpu",
      "cost_bearer_cost_dkk": 0.0,
      "cost_bearer_efficiency": null,
      "cost_bearer_waste_dkk": 0.0
    },
    "90d": {
      "jobs": 27,
      "completed_jobs": 10,
      "failed_jobs": 17,
      "cpu_hours_allocated": 40.444444,
      "measured_cpu_hours": 1.898889,
      "avg_cpu_efficiency": 0.07218,
      "jobs_with_measured_cpu": 18,
      "requested_mem_gb_hours": 397.74,
      "measured_mem_gb_max_sum": 20.954217,
      "avg_memory_efficiency": 0.010867,
      "jobs_with_measured_memory": 24,
      "estimated_cost_dkk": 6.463293,
      "underutilized_cost_dkk": 6.422709,
      "gpu_hours": 0.0,
      "cpu_cost_dkk": 2.628889,
      "mem_cost_dkk": 6.463275,
      "gpu_cost_dkk": 0.0,
      "cost_bearer": "memory",
      "cost_bearer_cost_dkk": 6.463275,
      "cost_bearer_efficiency": 0.010867,
      "cost_bearer_waste_dkk": 6.422709
    }
  },
  "daily_trends": [
    {
      "report_date": "2026-04-28",
      "avg_cpu_efficiency": 0.024749999999999998,
      "avg_memory_efficiency": 0.000972163200378418,
      "estimated_cost_dkk": 0.07258333333333335,
      "underutilized_cost_dkk": 0.06722083333333334,
      "gpu_hours": 0.0
    },
    {
      "report_date": "2026-04-29",
      "avg_cpu_efficiency": 0.03559865070187873,
      "avg_memory_efficiency": 0.0019527212778727213,
      "estimated_cost_dkk": 6.161006944444445,
      "underutilized_cost_dkk": 6.151862462116282,
      "gpu_hours": 0.0
    },
    {
      "report_date": "2026-05-01",
      "avg_cpu_efficiency": 0.15076654523375835,
      "avg_memory_efficiency": 0.02383772921562195,
      "estimated_cost_dkk": 0.22970277777777778,
      "underutilized_cost_dkk": 0.2036253077275223,
      "gpu_hours": 0.0
    }
  ],
  "recommendations": [
    {
      "type": "cpu_efficiency",
      "severity": "high",
      "title": "Low measured CPU utilization",
      "suggestion": "Review CPU requests for recent jobs and reduce cores where wall time is not improving.",
      "confidence": "medium",
      "evidence": {
        "avg_cpu_efficiency": 0.07218,
        "jobs_with_measured_cpu": 18
      }
    },
    {
      "type": "memory_efficiency",
      "severity": "medium",
      "title": "Requested memory is much higher than MaxRSS",
      "suggestion": "Use observed MaxRSS as a guide for smaller future memory requests, leaving a safety margin.",
      "confidence": "medium",
      "evidence": {
        "avg_memory_efficiency": 0.010867,
        "jobs_with_measured_memory": 24
      }
    }
  ],
  "top_inefficient_jobs": [
    {
      "report_date": "2026-04-29",
      "partition_name": "cpuqueue",
      "state": "COMPLETED",
      "alloc_cpus": 10,
      "elapsed_hours": 1.2577777777777779,
      "measured_cpu_efficiency": 0.01064487632508834,
      "memory_efficiency": 0.0012297821044921875,
      "gpu_count": 0,
      "estimated_cost_dkk": 2.043888888888889,
      "underutilized_cost_dkk": 2.041375350909763,
      "cpu_cost_dkk": 0.8175555555555557,
      "mem_cost_dkk": 2.043888888888889,
      "gpu_cost_dkk": 0.0,
      "cost_bearer": "memory",
      "cost_bearer_cost_dkk": 2.043888888888889,
      "cost_bearer_efficiency": 0.0012297821044921875,
      "cost_bearer_waste_dkk": 2.041375350909763
    },
    {
      "report_date": "2026-04-29",
      "partition_name": "cpuqueue",
      "state": "COMPLETED",
      "alloc_cpus": 10,
      "elapsed_hours": 1.24,
      "measured_cpu_efficiency": 0.010797491039426524,
      "memory_efficiency": 0.0012434864044189454,
      "gpu_count": 0,
      "estimated_cost_dkk": 2.015,
      "underutilized_cost_dkk": 2.012494374895096,
      "cpu_cost_dkk": 0.806,
      "mem_cost_dkk": 2.015,
      "gpu_cost_dkk": 0.0,
      "cost_bearer": "memory",
      "cost_bearer_cost_dkk": 2.015,
      "cost_bearer_efficiency": 0.0012434864044189454,
      "cost_bearer_waste_dkk": 2.012494374895096
    },
    {
      "report_date": "2026-04-29",
      "partition_name": "cpuqueue",
      "state": "COMPLETED",
      "alloc_cpus": 10,
      "elapsed_hours": 0.3036111111111111,
      "measured_cpu_efficiency": 0.027355901189387008,
      "memory_efficiency": 0.0011105823516845703,
      "gpu_count": 0,
      "estimated_cost_dkk": 0.4933680555555556,
      "underutilized_cost_dkk": 0.49282012970017064,
      "cpu_cost_dkk": 0.19734722222222223,
      "mem_cost_dkk": 0.4933680555555556,
      "gpu_cost_dkk": 0.0,
      "cost_bearer": "memory",
      "cost_bearer_cost_dkk": 0.4933680555555556,
      "cost_bearer_efficiency": 0.0011105823516845703,
      "cost_bearer_waste_dkk": 0.49282012970017064
    },
    {
      "report_date": "2026-04-29",
      "partition_name": "cpuqueue",
      "state": "COMPLETED",
      "alloc_cpus": 10,
      "elapsed_hours": 0.22972222222222222,
      "measured_cpu_efficiency": 0.0313180169286578,
      "memory_efficiency": 0.0011997222900390625,
      "gpu_count": 0,
      "estimated_cost_dkk": 0.3732986111111111,
      "underutilized_cost_dkk": 0.3728507564465205,
      "cpu_cost_dkk": 0.14931944444444445,
      "mem_cost_dkk": 0.3732986111111111,
      "gpu_cost_dkk": 0.0,
      "cost_bearer": "memory",
      "cost_bearer_cost_dkk": 0.3732986111111111,
      "cost_bearer_efficiency": 0.0011997222900390625,
      "cost_bearer_waste_dkk": 0.3728507564465205
    },
    {
      "report_date": "2026-04-29",
      "partition_name": "cpuqueue",
      "state": "COMPLETED",
      "alloc_cpus": 10,
      "elapsed_hours": 0.19111111111111112,
      "measured_cpu_efficiency": 0.02572674418604651,
      "memory_efficiency": 0.003166828155517578,
      "gpu_count": 0,
      "estimated_cost_dkk": 0.3105555555555556,
      "underutilized_cost_dkk": 0.30957207947836984,
      "cpu_cost_dkk": 0.12422222222222223,
      "mem_cost_dkk": 0.3105555555555556,
      "gpu_cost_dkk": 0.0,
      "cost_bearer": "memory",
      "cost_bearer_cost_dkk": 0.3105555555555556,
      "cost_bearer_efficiency": 0.003166828155517578,
      "cost_bearer_waste_dkk": 0.30957207947836984
    },
    {
      "report_date": "2026-04-29",
      "partition_name": "cpuqueue",
      "state": "COMPLETED",
      "alloc_cpus": 10,
      "elapsed_hours": 0.1897222222222222,
      "measured_cpu_efficiency": 0.032210834553440704,
      "memory_efficiency": 0.0010807418823242188,
      "gpu_count": 0,
      "estimated_cost_dkk": 0.3082986111111111,
      "underutilized_cost_dkk": 0.30796541988982096,
      "cpu_cost_dkk": 0.12331944444444444,
      "mem_cost_dkk": 0.3082986111111111,
      "gpu_cost_dkk": 0.0,
      "cost_bearer": "memory",
      "cost_bearer_cost_dkk": 0.3082986111111111,
      "cost_bearer_efficiency": 0.0010807418823242188,
      "cost_bearer_waste_dkk": 0.30796541988982096
    },
    {
      "report_date": "2026-04-29",
      "partition_name": "cpuqueue",
      "state": "COMPLETED",
      "alloc_cpus": 10,
      "elapsed_hours": 0.15333333333333332,
      "measured_cpu_efficiency": 0.028985507246376812,
      "memory_efficiency": 0.0030636310577392576,
      "gpu_count": 0,
      "estimated_cost_dkk": 0.24916666666666665,
      "underutilized_cost_dkk": 0.2484033119281133,
      "cpu_cost_dkk": 0.09966666666666667,
      "mem_cost_dkk": 0.24916666666666665,
      "gpu_cost_dkk": 0.0,
      "cost_bearer": "memory",
      "cost_bearer_cost_dkk": 0.24916666666666665,
      "cost_bearer_efficiency": 0.0030636310577392576,
      "cost_bearer_waste_dkk": 0.2484033119281133
    },
    {
      "report_date": "2026-04-29",
      "partition_name": "cpuqueue",
      "state": "COMPLETED",
      "alloc_cpus": 10,
      "elapsed_hours": 0.1527777777777778,
      "measured_cpu_efficiency": 0.028727272727272726,
      "memory_efficiency": 0.003071460723876953,
      "gpu_count": 0,
      "estimated_cost_dkk": 0.24826388888888892,
      "underutilized_cost_dkk": 0.24750135610500973,
      "cpu_cost_dkk": 0.09930555555555556,
      "mem_cost_dkk": 0.24826388888888892,
      "gpu_cost_dkk": 0.0,
      "cost_bearer": "memory",
      "cost_bearer_cost_dkk": 0.24826388888888892,
      "cost_bearer_efficiency": 0.003071460723876953,
      "cost_bearer_waste_dkk": 0.24750135610500973
    },
    {
      "report_date": "2026-05-01",
      "partition_name": "cpuqueue",
      "state": "COMPLETED",
      "alloc_cpus": 8,
      "elapsed_hours": 0.1525,
      "measured_cpu_efficiency": 0.9045992714025501,
      "memory_efficiency": 0.12530890703201295,
      "gpu_count": 0,
      "estimated_cost_dkk": 0.19824999999999998,
      "underutilized_cost_dkk": 0.17340750918090342,
      "cpu_cost_dkk": 0.0793,
      "mem_cost_dkk": 0.19824999999999998,
      "gpu_cost_dkk": 0.0,
      "cost_bearer": "memory",
      "cost_bearer_cost_dkk": 0.19824999999999998,
      "cost_bearer_efficiency": 0.12530890703201295,
      "cost_bearer_waste_dkk": 0.17340750918090342
    },
    {
      "report_date": "2026-04-29",
      "partition_name": "cpuqueue",
      "state": "COMPLETED",
      "alloc_cpus": 10,
      "elapsed_hours": 0.07333333333333333,
      "measured_cpu_efficiency": 0.12462121212121212,
      "memory_efficiency": 0.0024082565307617185,
      "gpu_count": 0,
      "estimated_cost_dkk": 0.11916666666666667,
      "underutilized_cost_dkk": 0.11887968276341757,
      "cpu_cost_dkk": 0.04766666666666667,
      "mem_cost_dkk": 0.11916666666666667,
      "gpu_cost_dkk": 0.0,
      "cost_bearer": "memory",
      "cost_bearer_cost_dkk": 0.11916666666666667,
      "cost_bearer_efficiency": 0.0024082565307617185,
      "cost_bearer_waste_dkk": 0.11887968276341757
    }
  ],
  "public_user_id": "usr_0430126b4c9c",
  "display_pseudonym": "Scarlet Harbor",
  "personal_route_token": "u_a84b564d4264fea07dbcb8300569f0bc",
  "percentile_position": {
    "overall": 19.9,
    "cpu": 20.2,
    "memory": 16.4,
    "savings": 23.1
  },
  "peer_comparisons": [
    {
      "display_pseudonym": "Polar Juniper",
      "avg_cpu_efficiency": 0.6218628124289237,
      "avg_memory_efficiency": 0.18243706811042057,
      "underutilized_cost_dkk": 580.4869316827543,
      "percentile_position": 56.2
    },
    {
      "display_pseudonym": "Red Crane",
      "avg_cpu_efficiency": 9.111221249367261e-06,
      "avg_memory_efficiency": 0.06039978563785553,
      "underutilized_cost_dkk": 13.870295833333333,
      "percentile_position": 26.9
    },
    {
      "display_pseudonym": "Solar Comet",
      "avg_cpu_efficiency": 0.1636796770070031,
      "avg_memory_efficiency": 0.22387709112521625,
      "underutilized_cost_dkk": 15179.174270456788,
      "percentile_position": 94.6
    }
  ]
}
