{
  "schema_version": "analytics-v1",
  "generated_at": "2026-07-02T22:25:38Z",
  "all_time_summary": {
    "jobs": 50,
    "completed_jobs": 27,
    "failed_jobs": 23,
    "cpu_hours_allocated": 501.358611,
    "measured_cpu_hours": 0.307778,
    "avg_cpu_efficiency": 0.036008,
    "jobs_with_measured_cpu": 10,
    "requested_mem_gb_hours": 1305.943889,
    "measured_mem_gb_max_sum": 2.221989,
    "avg_memory_efficiency": 0.005148,
    "jobs_with_measured_memory": 11,
    "estimated_cost_dkk": 33.223152,
    "underutilized_cost_dkk": 0.137213,
    "gpu_hours": 0.0,
    "cpu_cost_dkk": 32.58831,
    "mem_cost_dkk": 21.221588,
    "gpu_cost_dkk": 0.0,
    "cost_bearer": "cpu",
    "cost_bearer_cost_dkk": 32.58831,
    "cost_bearer_efficiency": 0.036008,
    "cost_bearer_waste_dkk": 0.137213,
    "leaf_index": 2,
    "leaf_index_components": [
      {
        "id": "cpu",
        "label": "CPU efficiency",
        "value": 0.036,
        "weight": 0.6,
        "contribution": 0.0216
      },
      {
        "id": "memory",
        "label": "Memory efficiency",
        "value": 0.0051,
        "weight": 0.4,
        "contribution": 0.0021
      }
    ]
  },
  "rolling_summaries": {
    "7d": {
      "jobs": 0,
      "completed_jobs": 0,
      "failed_jobs": 0,
      "cpu_hours_allocated": 0.0,
      "measured_cpu_hours": 0.0,
      "avg_cpu_efficiency": null,
      "jobs_with_measured_cpu": 0,
      "requested_mem_gb_hours": 0.0,
      "measured_mem_gb_max_sum": 0.0,
      "avg_memory_efficiency": null,
      "jobs_with_measured_memory": 0,
      "estimated_cost_dkk": 0.0,
      "underutilized_cost_dkk": 0.0,
      "gpu_hours": 0.0,
      "cpu_cost_dkk": 0.0,
      "mem_cost_dkk": 0.0,
      "gpu_cost_dkk": 0.0,
      "cost_bearer": "cpu",
      "cost_bearer_cost_dkk": 0.0,
      "cost_bearer_efficiency": null,
      "cost_bearer_waste_dkk": 0.0,
      "leaf_index": null,
      "leaf_index_components": []
    },
    "30d": {
      "jobs": 0,
      "completed_jobs": 0,
      "failed_jobs": 0,
      "cpu_hours_allocated": 0.0,
      "measured_cpu_hours": 0.0,
      "avg_cpu_efficiency": null,
      "jobs_with_measured_cpu": 0,
      "requested_mem_gb_hours": 0.0,
      "measured_mem_gb_max_sum": 0.0,
      "avg_memory_efficiency": null,
      "jobs_with_measured_memory": 0,
      "estimated_cost_dkk": 0.0,
      "underutilized_cost_dkk": 0.0,
      "gpu_hours": 0.0,
      "cpu_cost_dkk": 0.0,
      "mem_cost_dkk": 0.0,
      "gpu_cost_dkk": 0.0,
      "cost_bearer": "cpu",
      "cost_bearer_cost_dkk": 0.0,
      "cost_bearer_efficiency": null,
      "cost_bearer_waste_dkk": 0.0,
      "leaf_index": null,
      "leaf_index_components": []
    },
    "90d": {
      "jobs": 1,
      "completed_jobs": 1,
      "failed_jobs": 0,
      "cpu_hours_allocated": 0.133333,
      "measured_cpu_hours": 0.009167,
      "avg_cpu_efficiency": 0.06875,
      "jobs_with_measured_cpu": 1,
      "requested_mem_gb_hours": 0.266667,
      "measured_mem_gb_max_sum": 0.002266,
      "avg_memory_efficiency": 0.001133,
      "jobs_with_measured_memory": 1,
      "estimated_cost_dkk": 0.008667,
      "underutilized_cost_dkk": 0.008071,
      "gpu_hours": 0.0,
      "cpu_cost_dkk": 0.008667,
      "mem_cost_dkk": 0.004333,
      "gpu_cost_dkk": 0.0,
      "cost_bearer": "cpu",
      "cost_bearer_cost_dkk": 0.008667,
      "cost_bearer_efficiency": 0.06875,
      "cost_bearer_waste_dkk": 0.008071,
      "leaf_index": 4,
      "leaf_index_components": [
        {
          "id": "cpu",
          "label": "CPU efficiency",
          "value": 0.0688,
          "weight": 0.6,
          "contribution": 0.0413
        },
        {
          "id": "memory",
          "label": "Memory efficiency",
          "value": 0.0011,
          "weight": 0.4,
          "contribution": 0.0005
        }
      ]
    },
    "180d": {
      "jobs": 4,
      "completed_jobs": 2,
      "failed_jobs": 2,
      "cpu_hours_allocated": 0.155556,
      "measured_cpu_hours": 0.009167,
      "avg_cpu_efficiency": 0.06875,
      "jobs_with_measured_cpu": 1,
      "requested_mem_gb_hours": 0.444444,
      "measured_mem_gb_max_sum": 0.002266,
      "avg_memory_efficiency": 0.001133,
      "jobs_with_measured_memory": 1,
      "estimated_cost_dkk": 0.011556,
      "underutilized_cost_dkk": 0.008071,
      "gpu_hours": 0.0,
      "cpu_cost_dkk": 0.010111,
      "mem_cost_dkk": 0.007222,
      "gpu_cost_dkk": 0.0,
      "cost_bearer": "cpu",
      "cost_bearer_cost_dkk": 0.010111,
      "cost_bearer_efficiency": 0.06875,
      "cost_bearer_waste_dkk": 0.008071,
      "leaf_index": 4,
      "leaf_index_components": [
        {
          "id": "cpu",
          "label": "CPU efficiency",
          "value": 0.0688,
          "weight": 0.6,
          "contribution": 0.0413
        },
        {
          "id": "memory",
          "label": "Memory efficiency",
          "value": 0.0011,
          "weight": 0.4,
          "contribution": 0.0005
        }
      ]
    }
  },
  "daily_trends": [
    {
      "report_date": "2024-06-23",
      "avg_cpu_efficiency": 0.03236976814212586,
      "avg_memory_efficiency": 0.005549306869506837,
      "estimated_cost_dkk": 0.13649999999999998,
      "underutilized_cost_dkk": 0.12914265605741074,
      "gpu_hours": 0.0,
      "jobs": 10,
      "jobs_with_measured_cpu": 9,
      "jobs_with_measured_memory": 10,
      "cpu_hours_allocated": 1.0499999999999998,
      "measured_cpu_hours": 0.2986111111111111,
      "requested_mem_gb_hours": 8.399999999999999,
      "measured_mem_gb_max_sum": 2.2197227478027344
    },
    {
      "report_date": "2024-08-19",
      "avg_cpu_efficiency": null,
      "avg_memory_efficiency": null,
      "estimated_cost_dkk": 4.483555555555556,
      "underutilized_cost_dkk": 0.0,
      "gpu_hours": 0.0,
      "jobs": 5,
      "jobs_with_measured_cpu": 0,
      "jobs_with_measured_memory": 0,
      "cpu_hours_allocated": 68.97777777777777,
      "measured_cpu_hours": 0.0,
      "requested_mem_gb_hours": 172.44444444444443,
      "measured_mem_gb_max_sum": 0.0
    },
    {
      "report_date": "2024-08-20",
      "avg_cpu_efficiency": null,
      "avg_memory_efficiency": null,
      "estimated_cost_dkk": 0.4630166666666667,
      "underutilized_cost_dkk": 0.0,
      "gpu_hours": 0.0,
      "jobs": 1,
      "jobs_with_measured_cpu": 0,
      "jobs_with_measured_memory": 0,
      "cpu_hours_allocated": 7.123333333333333,
      "measured_cpu_hours": 0.0,
      "requested_mem_gb_hours": 23.744444444444444,
      "measured_mem_gb_max_sum": 0.0
    },
    {
      "report_date": "2024-09-06",
      "avg_cpu_efficiency": null,
      "avg_memory_efficiency": null,
      "estimated_cost_dkk": 0.66015625,
      "underutilized_cost_dkk": 0.0,
      "gpu_hours": 0.0,
      "jobs": 4,
      "jobs_with_measured_cpu": 0,
      "jobs_with_measured_memory": 0,
      "cpu_hours_allocated": 3.4291666666666663,
      "measured_cpu_hours": 0.0,
      "requested_mem_gb_hours": 40.625,
      "measured_mem_gb_max_sum": 0.0
    },
    {
      "report_date": "2024-09-09",
      "avg_cpu_efficiency": null,
      "avg_memory_efficiency": null,
      "estimated_cost_dkk": 0.029114583333333336,
      "underutilized_cost_dkk": 0.0,
      "gpu_hours": 0.0,
      "jobs": 8,
      "jobs_with_measured_cpu": 0,
      "jobs_with_measured_memory": 0,
      "cpu_hours_allocated": 0.17916666666666664,
      "measured_cpu_hours": 0.0,
      "requested_mem_gb_hours": 1.7916666666666667,
      "measured_mem_gb_max_sum": 0.0
    },
    {
      "report_date": "2024-09-12",
      "avg_cpu_efficiency": null,
      "avg_memory_efficiency": null,
      "estimated_cost_dkk": 0.09366319444444443,
      "underutilized_cost_dkk": 0.0,
      "gpu_hours": 0.0,
      "jobs": 7,
      "jobs_with_measured_cpu": 0,
      "jobs_with_measured_memory": 0,
      "cpu_hours_allocated": 0.23055555555555554,
      "measured_cpu_hours": 0.0,
      "requested_mem_gb_hours": 5.763888888888889,
      "measured_mem_gb_max_sum": 0.0
    },
    {
      "report_date": "2025-05-31",
      "avg_cpu_efficiency": null,
      "avg_memory_efficiency": null,
      "estimated_cost_dkk": 0.04232222222222222,
      "underutilized_cost_dkk": 0.0,
      "gpu_hours": 0.0,
      "jobs": 8,
      "jobs_with_measured_cpu": 0,
      "jobs_with_measured_memory": 0,
      "cpu_hours_allocated": 0.16277777777777777,
      "measured_cpu_hours": 0.0,
      "requested_mem_gb_hours": 2.6044444444444443,
      "measured_mem_gb_max_sum": 0.0
    },
    {
      "report_date": "2025-10-08",
      "avg_cpu_efficiency": null,
      "avg_memory_efficiency": null,
      "estimated_cost_dkk": 1.4101569444444444,
      "underutilized_cost_dkk": 0.0,
      "gpu_hours": 0.0,
      "jobs": 2,
      "jobs_with_measured_cpu": 0,
      "jobs_with_measured_memory": 0,
      "cpu_hours_allocated": 21.69472222222222,
      "measured_cpu_hours": 0.0,
      "requested_mem_gb_hours": 54.236666666666665,
      "measured_mem_gb_max_sum": 0.0
    },
    {
      "report_date": "2025-10-09",
      "avg_cpu_efficiency": null,
      "avg_memory_efficiency": null,
      "estimated_cost_dkk": 25.893111111111114,
      "underutilized_cost_dkk": 0.0,
      "gpu_hours": 0.0,
      "jobs": 1,
      "jobs_with_measured_cpu": 0,
      "jobs_with_measured_memory": 0,
      "cpu_hours_allocated": 398.3555555555556,
      "measured_cpu_hours": 0.0,
      "requested_mem_gb_hours": 995.8888888888889,
      "measured_mem_gb_max_sum": 0.0
    },
    {
      "report_date": "2026-03-01",
      "avg_cpu_efficiency": null,
      "avg_memory_efficiency": null,
      "estimated_cost_dkk": 0.0028888888888888888,
      "underutilized_cost_dkk": 0.0,
      "gpu_hours": 0.0,
      "jobs": 3,
      "jobs_with_measured_cpu": 0,
      "jobs_with_measured_memory": 0,
      "cpu_hours_allocated": 0.022222222222222223,
      "measured_cpu_hours": 0.0,
      "requested_mem_gb_hours": 0.17777777777777778,
      "measured_mem_gb_max_sum": 0.0
    },
    {
      "report_date": "2026-04-16",
      "avg_cpu_efficiency": 0.06875,
      "avg_memory_efficiency": 0.001132965087890625,
      "estimated_cost_dkk": 0.008666666666666666,
      "underutilized_cost_dkk": 0.008070833333333333,
      "gpu_hours": 0.0,
      "jobs": 1,
      "jobs_with_measured_cpu": 1,
      "jobs_with_measured_memory": 1,
      "cpu_hours_allocated": 0.13333333333333333,
      "measured_cpu_hours": 0.009166666666666667,
      "requested_mem_gb_hours": 0.26666666666666666,
      "measured_mem_gb_max_sum": 0.00226593017578125
    }
  ],
  "recommendations": [],
  "top_inefficient_jobs": [
    {
      "report_date": "2024-06-23",
      "partition_name": "cpuqueue",
      "state": "COMPLETED",
      "alloc_cpus": 5,
      "elapsed_hours": 0.205,
      "measured_cpu_efficiency": 0.29132791327913277,
      "memory_efficiency": 0.05521383285522461,
      "gpu_count": 0,
      "estimated_cost_dkk": 0.13324999999999998,
      "underutilized_cost_dkk": 0.1258927567720413,
      "cpu_cost_dkk": 0.06662499999999999,
      "mem_cost_dkk": 0.13324999999999998,
      "gpu_cost_dkk": 0.0,
      "cost_bearer": "memory",
      "cost_bearer_cost_dkk": 0.13324999999999998,
      "cost_bearer_efficiency": 0.05521383285522461,
      "cost_bearer_waste_dkk": 0.1258927567720413
    },
    {
      "report_date": "2026-04-16",
      "partition_name": "cpuqueue",
      "state": "COMPLETED",
      "alloc_cpus": 1,
      "elapsed_hours": 0.13333333333333333,
      "measured_cpu_efficiency": 0.06875,
      "memory_efficiency": 0.001132965087890625,
      "gpu_count": 0,
      "estimated_cost_dkk": 0.008666666666666666,
      "underutilized_cost_dkk": 0.008070833333333333,
      "cpu_cost_dkk": 0.008666666666666666,
      "mem_cost_dkk": 0.004333333333333333,
      "gpu_cost_dkk": 0.0,
      "cost_bearer": "cpu",
      "cost_bearer_cost_dkk": 0.008666666666666666,
      "cost_bearer_efficiency": 0.06875,
      "cost_bearer_waste_dkk": 0.008070833333333333
    },
    {
      "report_date": "2024-06-23",
      "partition_name": "cpuqueue",
      "state": "COMPLETED",
      "alloc_cpus": 5,
      "elapsed_hours": 0.0019444444444444444,
      "measured_cpu_efficiency": 0.0,
      "memory_efficiency": 3.0994415283203125e-05,
      "gpu_count": 0,
      "estimated_cost_dkk": 0.001263888888888889,
      "underutilized_cost_dkk": 0.001263849715391795,
      "cpu_cost_dkk": 0.0006319444444444445,
      "mem_cost_dkk": 0.001263888888888889,
      "gpu_cost_dkk": 0.0,
      "cost_bearer": "memory",
      "cost_bearer_cost_dkk": 0.001263888888888889,
      "cost_bearer_efficiency": 3.0994415283203125e-05,
      "cost_bearer_waste_dkk": 0.001263849715391795
    },
    {
      "report_date": "2024-06-23",
      "partition_name": "cpuqueue",
      "state": "COMPLETED",
      "alloc_cpus": 5,
      "elapsed_hours": 0.0011111111111111111,
      "measured_cpu_efficiency": 0.0,
      "memory_efficiency": 3.08990478515625e-05,
      "gpu_count": 0,
      "estimated_cost_dkk": 0.0007222222222222223,
      "underutilized_cost_dkk": 0.0007221999062432184,
      "cpu_cost_dkk": 0.00036111111111111115,
      "mem_cost_dkk": 0.0007222222222222223,
      "gpu_cost_dkk": 0.0,
      "cost_bearer": "memory",
      "cost_bearer_cost_dkk": 0.0007222222222222223,
      "cost_bearer_efficiency": 3.08990478515625e-05,
      "cost_bearer_waste_dkk": 0.0007221999062432184
    },
    {
      "report_date": "2024-06-23",
      "partition_name": "cpuqueue",
      "state": "COMPLETED",
      "alloc_cpus": 5,
      "elapsed_hours": 0.0005555555555555556,
      "measured_cpu_efficiency": 0.0,
      "memory_efficiency": 3.108978271484375e-05,
      "gpu_count": 0,
      "estimated_cost_dkk": 0.00036111111111111115,
      "underutilized_cost_dkk": 0.0003610998842451308,
      "cpu_cost_dkk": 0.00018055555555555557,
      "mem_cost_dkk": 0.00036111111111111115,
      "gpu_cost_dkk": 0.0,
      "cost_bearer": "memory",
      "cost_bearer_cost_dkk": 0.00036111111111111115,
      "cost_bearer_efficiency": 3.108978271484375e-05,
      "cost_bearer_waste_dkk": 0.0003610998842451308
    },
    {
      "report_date": "2024-06-23",
      "partition_name": "cpuqueue",
      "state": "COMPLETED",
      "alloc_cpus": 5,
      "elapsed_hours": 0.0002777777777777778,
      "measured_cpu_efficiency": 0.0,
      "memory_efficiency": 3.08990478515625e-05,
      "gpu_count": 0,
      "estimated_cost_dkk": 0.00018055555555555557,
      "underutilized_cost_dkk": 0.0001805499765608046,
      "cpu_cost_dkk": 9.027777777777779e-05,
      "mem_cost_dkk": 0.00018055555555555557,
      "gpu_cost_dkk": 0.0,
      "cost_bearer": "memory",
      "cost_bearer_cost_dkk": 0.00018055555555555557,
      "cost_bearer_efficiency": 3.08990478515625e-05,
      "cost_bearer_waste_dkk": 0.0001805499765608046
    },
    {
      "report_date": "2024-06-23",
      "partition_name": "cpuqueue",
      "state": "COMPLETED",
      "alloc_cpus": 5,
      "elapsed_hours": 0.0002777777777777778,
      "measured_cpu_efficiency": 0.0,
      "memory_efficiency": 3.0994415283203125e-05,
      "gpu_count": 0,
      "estimated_cost_dkk": 0.00018055555555555557,
      "underutilized_cost_dkk": 0.00018054995934168499,
      "cpu_cost_dkk": 9.027777777777779e-05,
      "mem_cost_dkk": 0.00018055555555555557,
      "gpu_cost_dkk": 0.0,
      "cost_bearer": "memory",
      "cost_bearer_cost_dkk": 0.00018055555555555557,
      "cost_bearer_efficiency": 3.0994415283203125e-05,
      "cost_bearer_waste_dkk": 0.00018054995934168499
    },
    {
      "report_date": "2024-06-23",
      "partition_name": "cpuqueue",
      "state": "COMPLETED",
      "alloc_cpus": 5,
      "elapsed_hours": 0.0002777777777777778,
      "measured_cpu_efficiency": 0.0,
      "memory_efficiency": 3.0994415283203125e-05,
      "gpu_count": 0,
      "estimated_cost_dkk": 0.00018055555555555557,
      "underutilized_cost_dkk": 0.00018054995934168499,
      "cpu_cost_dkk": 9.027777777777779e-05,
      "mem_cost_dkk": 0.00018055555555555557,
      "gpu_cost_dkk": 0.0,
      "cost_bearer": "memory",
      "cost_bearer_cost_dkk": 0.00018055555555555557,
      "cost_bearer_efficiency": 3.0994415283203125e-05,
      "cost_bearer_waste_dkk": 0.00018054995934168499
    },
    {
      "report_date": "2024-06-23",
      "partition_name": "cpuqueue",
      "state": "COMPLETED",
      "alloc_cpus": 5,
      "elapsed_hours": 0.0002777777777777778,
      "measured_cpu_efficiency": 0.0,
      "memory_efficiency": 3.108978271484375e-05,
      "gpu_count": 0,
      "estimated_cost_dkk": 0.00018055555555555557,
      "underutilized_cost_dkk": 0.0001805499421225654,
      "cpu_cost_dkk": 9.027777777777779e-05,
      "mem_cost_dkk": 0.00018055555555555557,
      "gpu_cost_dkk": 0.0,
      "cost_bearer": "memory",
      "cost_bearer_cost_dkk": 0.00018055555555555557,
      "cost_bearer_efficiency": 3.108978271484375e-05,
      "cost_bearer_waste_dkk": 0.0001805499421225654
    },
    {
      "report_date": "2024-06-23",
      "partition_name": "cpuqueue",
      "state": "COMPLETED",
      "alloc_cpus": 5,
      "elapsed_hours": 0.0002777777777777778,
      "measured_cpu_efficiency": 0.0,
      "memory_efficiency": 3.108978271484375e-05,
      "gpu_count": 0,
      "estimated_cost_dkk": 0.00018055555555555557,
      "underutilized_cost_dkk": 0.0001805499421225654,
      "cpu_cost_dkk": 9.027777777777779e-05,
      "mem_cost_dkk": 0.00018055555555555557,
      "gpu_cost_dkk": 0.0,
      "cost_bearer": "memory",
      "cost_bearer_cost_dkk": 0.00018055555555555557,
      "cost_bearer_efficiency": 3.108978271484375e-05,
      "cost_bearer_waste_dkk": 0.0001805499421225654
    }
  ],
  "leaf": {
    "version": "2.0",
    "window_days": 180,
    "leaf_index": 4,
    "leaf_index_components": [
      {
        "id": "cpu",
        "label": "CPU efficiency",
        "value": 0.0688,
        "weight": 0.6,
        "contribution": 0.0413
      },
      {
        "id": "memory",
        "label": "Memory efficiency",
        "value": 0.0011,
        "weight": 0.4,
        "contribution": 0.0005
      }
    ],
    "confidence": "very_low",
    "measurement_coverage": {
      "jobs_measured": 1,
      "jobs_excluded": 3,
      "jobs_measured_pct": 25.0,
      "cpu_hours_measured_pct": 5.89,
      "memory_measured_pct": 0.51
    },
    "percentile": 16.5
  },
  "public_user_id": "usr_64f37eb1bdb6",
  "display_pseudonym": "Slate Condor",
  "personal_route_token": "u_c9ed1be115650390e746de623e2f43e6",
  "username": "knb401",
  "percentile_position": {
    "overall": 9.2,
    "cpu": 17.7,
    "memory": 6.2,
    "savings": 3.8
  },
  "peer_comparisons": [
    {
      "display_pseudonym": "Bright Aster",
      "avg_cpu_efficiency": 0.05125503883845109,
      "avg_memory_efficiency": 0.04112347469064925,
      "underutilized_cost_dkk": 91.37399153067933,
      "percentile_position": 42.0
    },
    {
      "display_pseudonym": "White Comet",
      "avg_cpu_efficiency": 0.4438217911912119,
      "avg_memory_efficiency": 0.560293698104327,
      "underutilized_cost_dkk": 365.9551869049887,
      "percentile_position": 51.1
    },
    {
      "display_pseudonym": "Azure Condor",
      "avg_cpu_efficiency": 0.18451103604894492,
      "avg_memory_efficiency": 0.12220264439705053,
      "underutilized_cost_dkk": 466.83067105498844,
      "percentile_position": 52.7
    }
  ]
}
