{
  "schema_version": "analytics-v1",
  "generated_at": "2026-07-01T09:08:14Z",
  "all_time_summary": {
    "jobs": 215,
    "completed_jobs": 173,
    "failed_jobs": 42,
    "cpu_hours_allocated": 9359.333889,
    "measured_cpu_hours": 0.315278,
    "avg_cpu_efficiency": 0.240951,
    "jobs_with_measured_cpu": 17,
    "requested_mem_gb_hours": 56293.812839,
    "measured_mem_gb_max_sum": 1.542023,
    "avg_memory_efficiency": 0.007049,
    "jobs_with_measured_memory": 17,
    "estimated_cost_dkk": 923.585235,
    "underutilized_cost_dkk": 0.108752,
    "gpu_hours": 0.0,
    "cpu_cost_dkk": 608.356703,
    "mem_cost_dkk": 914.774459,
    "gpu_cost_dkk": 0.0,
    "cost_bearer": "memory",
    "cost_bearer_cost_dkk": 914.774459,
    "cost_bearer_efficiency": 0.007049,
    "cost_bearer_waste_dkk": 0.108752
  },
  "rolling_summaries": {
    "7d": {
      "jobs": 0,
      "completed_jobs": 0,
      "failed_jobs": 0,
      "cpu_hours_allocated": 0.0,
      "measured_cpu_hours": 0.0,
      "avg_cpu_efficiency": null,
      "jobs_with_measured_cpu": 0,
      "requested_mem_gb_hours": 0.0,
      "measured_mem_gb_max_sum": 0.0,
      "avg_memory_efficiency": null,
      "jobs_with_measured_memory": 0,
      "estimated_cost_dkk": 0.0,
      "underutilized_cost_dkk": 0.0,
      "gpu_hours": 0.0,
      "cpu_cost_dkk": 0.0,
      "mem_cost_dkk": 0.0,
      "gpu_cost_dkk": 0.0,
      "cost_bearer": "cpu",
      "cost_bearer_cost_dkk": 0.0,
      "cost_bearer_efficiency": null,
      "cost_bearer_waste_dkk": 0.0
    },
    "30d": {
      "jobs": 0,
      "completed_jobs": 0,
      "failed_jobs": 0,
      "cpu_hours_allocated": 0.0,
      "measured_cpu_hours": 0.0,
      "avg_cpu_efficiency": null,
      "jobs_with_measured_cpu": 0,
      "requested_mem_gb_hours": 0.0,
      "measured_mem_gb_max_sum": 0.0,
      "avg_memory_efficiency": null,
      "jobs_with_measured_memory": 0,
      "estimated_cost_dkk": 0.0,
      "underutilized_cost_dkk": 0.0,
      "gpu_hours": 0.0,
      "cpu_cost_dkk": 0.0,
      "mem_cost_dkk": 0.0,
      "gpu_cost_dkk": 0.0,
      "cost_bearer": "cpu",
      "cost_bearer_cost_dkk": 0.0,
      "cost_bearer_efficiency": null,
      "cost_bearer_waste_dkk": 0.0
    },
    "90d": {
      "jobs": 0,
      "completed_jobs": 0,
      "failed_jobs": 0,
      "cpu_hours_allocated": 0.0,
      "measured_cpu_hours": 0.0,
      "avg_cpu_efficiency": null,
      "jobs_with_measured_cpu": 0,
      "requested_mem_gb_hours": 0.0,
      "measured_mem_gb_max_sum": 0.0,
      "avg_memory_efficiency": null,
      "jobs_with_measured_memory": 0,
      "estimated_cost_dkk": 0.0,
      "underutilized_cost_dkk": 0.0,
      "gpu_hours": 0.0,
      "cpu_cost_dkk": 0.0,
      "mem_cost_dkk": 0.0,
      "gpu_cost_dkk": 0.0,
      "cost_bearer": "cpu",
      "cost_bearer_cost_dkk": 0.0,
      "cost_bearer_efficiency": null,
      "cost_bearer_waste_dkk": 0.0
    }
  },
  "daily_trends": [
    {
      "report_date": "2024-06-27",
      "avg_cpu_efficiency": 0.2409507014762982,
      "avg_memory_efficiency": 0.007048870223799562,
      "estimated_cost_dkk": 0.10985,
      "underutilized_cost_dkk": 0.10875223532252842,
      "gpu_hours": 0.0
    },
    {
      "report_date": "2024-07-29",
      "avg_cpu_efficiency": null,
      "avg_memory_efficiency": null,
      "estimated_cost_dkk": 1.6677916666666668,
      "underutilized_cost_dkk": 0.0,
      "gpu_hours": 0.0
    },
    {
      "report_date": "2024-07-31",
      "avg_cpu_efficiency": null,
      "avg_memory_efficiency": null,
      "estimated_cost_dkk": 1.8192416666666669,
      "underutilized_cost_dkk": 0.0,
      "gpu_hours": 0.0
    },
    {
      "report_date": "2024-08-02",
      "avg_cpu_efficiency": null,
      "avg_memory_efficiency": null,
      "estimated_cost_dkk": 73.08708333333333,
      "underutilized_cost_dkk": 0.0,
      "gpu_hours": 0.0
    },
    {
      "report_date": "2024-08-04",
      "avg_cpu_efficiency": null,
      "avg_memory_efficiency": null,
      "estimated_cost_dkk": 182.72908333333334,
      "underutilized_cost_dkk": 0.0,
      "gpu_hours": 0.0
    },
    {
      "report_date": "2024-08-06",
      "avg_cpu_efficiency": null,
      "avg_memory_efficiency": null,
      "estimated_cost_dkk": 2.494104166666667,
      "underutilized_cost_dkk": 0.0,
      "gpu_hours": 0.0
    },
    {
      "report_date": "2024-08-07",
      "avg_cpu_efficiency": null,
      "avg_memory_efficiency": null,
      "estimated_cost_dkk": 41.96519166666666,
      "underutilized_cost_dkk": 0.0,
      "gpu_hours": 0.0
    },
    {
      "report_date": "2024-08-08",
      "avg_cpu_efficiency": null,
      "avg_memory_efficiency": null,
      "estimated_cost_dkk": 0.190775,
      "underutilized_cost_dkk": 0.0,
      "gpu_hours": 0.0
    },
    {
      "report_date": "2024-08-09",
      "avg_cpu_efficiency": null,
      "avg_memory_efficiency": null,
      "estimated_cost_dkk": 8.182272222222224,
      "underutilized_cost_dkk": 0.0,
      "gpu_hours": 0.0
    },
    {
      "report_date": "2024-08-12",
      "avg_cpu_efficiency": null,
      "avg_memory_efficiency": null,
      "estimated_cost_dkk": 1.565416666666667,
      "underutilized_cost_dkk": 0.0,
      "gpu_hours": 0.0
    },
    {
      "report_date": "2024-08-22",
      "avg_cpu_efficiency": null,
      "avg_memory_efficiency": null,
      "estimated_cost_dkk": 0.03954166666666667,
      "underutilized_cost_dkk": 0.0,
      "gpu_hours": 0.0
    },
    {
      "report_date": "2024-08-27",
      "avg_cpu_efficiency": null,
      "avg_memory_efficiency": null,
      "estimated_cost_dkk": 224.11079166666667,
      "underutilized_cost_dkk": 0.0,
      "gpu_hours": 0.0
    },
    {
      "report_date": "2024-09-06",
      "avg_cpu_efficiency": null,
      "avg_memory_efficiency": null,
      "estimated_cost_dkk": 0.0010833333333333333,
      "underutilized_cost_dkk": 0.0,
      "gpu_hours": 0.0
    },
    {
      "report_date": "2024-09-09",
      "avg_cpu_efficiency": null,
      "avg_memory_efficiency": null,
      "estimated_cost_dkk": 18.623041666666666,
      "underutilized_cost_dkk": 0.0,
      "gpu_hours": 0.0
    },
    {
      "report_date": "2024-09-10",
      "avg_cpu_efficiency": null,
      "avg_memory_efficiency": null,
      "estimated_cost_dkk": 1.8219500000000002,
      "underutilized_cost_dkk": 0.0,
      "gpu_hours": 0.0
    },
    {
      "report_date": "2024-09-15",
      "avg_cpu_efficiency": null,
      "avg_memory_efficiency": null,
      "estimated_cost_dkk": 249.89575000000002,
      "underutilized_cost_dkk": 0.0,
      "gpu_hours": 0.0
    },
    {
      "report_date": "2024-09-18",
      "avg_cpu_efficiency": null,
      "avg_memory_efficiency": null,
      "estimated_cost_dkk": 14.334666666666665,
      "underutilized_cost_dkk": 0.0,
      "gpu_hours": 0.0
    },
    {
      "report_date": "2024-09-20",
      "avg_cpu_efficiency": null,
      "avg_memory_efficiency": null,
      "estimated_cost_dkk": 43.355000000000004,
      "underutilized_cost_dkk": 0.0,
      "gpu_hours": 0.0
    },
    {
      "report_date": "2025-02-17",
      "avg_cpu_efficiency": null,
      "avg_memory_efficiency": null,
      "estimated_cost_dkk": 1.2320750000000003,
      "underutilized_cost_dkk": 0.0,
      "gpu_hours": 0.0
    },
    {
      "report_date": "2025-02-18",
      "avg_cpu_efficiency": null,
      "avg_memory_efficiency": null,
      "estimated_cost_dkk": 1.220320833333334,
      "underutilized_cost_dkk": 0.0,
      "gpu_hours": 0.0
    },
    {
      "report_date": "2025-02-20",
      "avg_cpu_efficiency": null,
      "avg_memory_efficiency": null,
      "estimated_cost_dkk": 42.8536875,
      "underutilized_cost_dkk": 0.0,
      "gpu_hours": 0.0
    },
    {
      "report_date": "2025-02-21",
      "avg_cpu_efficiency": null,
      "avg_memory_efficiency": null,
      "estimated_cost_dkk": 10.985000000000001,
      "underutilized_cost_dkk": 0.0,
      "gpu_hours": 0.0
    },
    {
      "report_date": "2025-08-29",
      "avg_cpu_efficiency": null,
      "avg_memory_efficiency": null,
      "estimated_cost_dkk": 1.1351166666666668,
      "underutilized_cost_dkk": 0.0,
      "gpu_hours": 0.0
    },
    {
      "report_date": "2025-11-21",
      "avg_cpu_efficiency": null,
      "avg_memory_efficiency": null,
      "estimated_cost_dkk": 0.1664,
      "underutilized_cost_dkk": 0.0,
      "gpu_hours": 0.0
    }
  ],
  "recommendations": [
    {
      "type": "cpu_efficiency",
      "severity": "high",
      "title": "Low measured CPU utilization",
      "suggestion": "Review CPU requests for recent jobs and reduce cores where wall time is not improving.",
      "confidence": "medium",
      "evidence": {
        "avg_cpu_efficiency": 0.240951,
        "jobs_with_measured_cpu": 17
      }
    },
    {
      "type": "memory_efficiency",
      "severity": "medium",
      "title": "Requested memory is much higher than MaxRSS",
      "suggestion": "Use observed MaxRSS as a guide for smaller future memory requests, leaving a safety margin.",
      "confidence": "medium",
      "evidence": {
        "avg_memory_efficiency": 0.007049,
        "jobs_with_measured_memory": 17
      }
    }
  ],
  "top_inefficient_jobs": [
    {
      "report_date": "2024-06-27",
      "partition_name": "cpuqueue",
      "state": "FAILED",
      "alloc_cpus": 24,
      "elapsed_hours": 0.008611111111111111,
      "measured_cpu_efficiency": 0.0,
      "memory_efficiency": 0.005946821636623806,
      "gpu_count": 0,
      "estimated_cost_dkk": 0.02015,
      "underutilized_cost_dkk": 0.02003017154402203,
      "cpu_cost_dkk": 0.013433333333333334,
      "mem_cost_dkk": 0.02015,
      "gpu_cost_dkk": 0.0,
      "cost_bearer": "memory",
      "cost_bearer_cost_dkk": 0.02015,
      "cost_bearer_efficiency": 0.005946821636623806,
      "cost_bearer_waste_dkk": 0.02003017154402203
    },
    {
      "report_date": "2024-06-27",
      "partition_name": "cpuqueue",
      "state": "COMPLETED",
      "alloc_cpus": 1,
      "elapsed_hours": 0.2011111111111111,
      "measured_cpu_efficiency": 0.1781767955801105,
      "memory_efficiency": 0.010553359985351562,
      "gpu_count": 0,
      "estimated_cost_dkk": 0.019608333333333332,
      "underutilized_cost_dkk": 0.019401399532953896,
      "cpu_cost_dkk": 0.013072222222222221,
      "mem_cost_dkk": 0.019608333333333332,
      "gpu_cost_dkk": 0.0,
      "cost_bearer": "memory",
      "cost_bearer_cost_dkk": 0.019608333333333332,
      "cost_bearer_efficiency": 0.010553359985351562,
      "cost_bearer_waste_dkk": 0.019401399532953896
    },
    {
      "report_date": "2024-06-27",
      "partition_name": "cpuqueue",
      "state": "COMPLETED",
      "alloc_cpus": 1,
      "elapsed_hours": 0.12111111111111111,
      "measured_cpu_efficiency": 0.2545871559633027,
      "memory_efficiency": 0.011014302571614584,
      "gpu_count": 0,
      "estimated_cost_dkk": 0.011808333333333334,
      "underutilized_cost_dkk": 0.011678272777133517,
      "cpu_cost_dkk": 0.007872222222222223,
      "mem_cost_dkk": 0.011808333333333334,
      "gpu_cost_dkk": 0.0,
      "cost_bearer": "memory",
      "cost_bearer_cost_dkk": 0.011808333333333334,
      "cost_bearer_efficiency": 0.011014302571614584,
      "cost_bearer_waste_dkk": 0.011678272777133517
    },
    {
      "report_date": "2024-06-27",
      "partition_name": "cpuqueue",
      "state": "COMPLETED",
      "alloc_cpus": 1,
      "elapsed_hours": 0.10611111111111111,
      "measured_cpu_efficiency": 0.3298429319371728,
      "memory_efficiency": 0.013503392537434896,
      "gpu_count": 0,
      "estimated_cost_dkk": 0.010345833333333334,
      "underutilized_cost_dkk": 0.010206129484706455,
      "cpu_cost_dkk": 0.006897222222222223,
      "mem_cost_dkk": 0.010345833333333334,
      "gpu_cost_dkk": 0.0,
      "cost_bearer": "memory",
      "cost_bearer_cost_dkk": 0.010345833333333334,
      "cost_bearer_efficiency": 0.013503392537434896,
      "cost_bearer_waste_dkk": 0.010206129484706455
    },
    {
      "report_date": "2024-06-27",
      "partition_name": "cpuqueue",
      "state": "COMPLETED",
      "alloc_cpus": 1,
      "elapsed_hours": 0.105,
      "measured_cpu_efficiency": 0.328042328042328,
      "memory_efficiency": 0.012045542399088541,
      "gpu_count": 0,
      "estimated_cost_dkk": 0.0102375,
      "underutilized_cost_dkk": 0.010114183759689331,
      "cpu_cost_dkk": 0.006825,
      "mem_cost_dkk": 0.0102375,
      "gpu_cost_dkk": 0.0,
      "cost_bearer": "memory",
      "cost_bearer_cost_dkk": 0.0102375,
      "cost_bearer_efficiency": 0.012045542399088541,
      "cost_bearer_waste_dkk": 0.010114183759689331
    },
    {
      "report_date": "2024-06-27",
      "partition_name": "cpuqueue",
      "state": "COMPLETED",
      "alloc_cpus": 1,
      "elapsed_hours": 0.06416666666666666,
      "measured_cpu_efficiency": 0.42857142857142855,
      "memory_efficiency": 0.011104583740234375,
      "gpu_count": 0,
      "estimated_cost_dkk": 0.0062562500000000005,
      "underutilized_cost_dkk": 0.006186776947975159,
      "cpu_cost_dkk": 0.004170833333333334,
      "mem_cost_dkk": 0.0062562500000000005,
      "gpu_cost_dkk": 0.0,
      "cost_bearer": "memory",
      "cost_bearer_cost_dkk": 0.0062562500000000005,
      "cost_bearer_efficiency": 0.011104583740234375,
      "cost_bearer_waste_dkk": 0.006186776947975159
    },
    {
      "report_date": "2024-06-27",
      "partition_name": "cpuqueue",
      "state": "COMPLETED",
      "alloc_cpus": 1,
      "elapsed_hours": 0.0636111111111111,
      "measured_cpu_efficiency": 0.44541484716157204,
      "memory_efficiency": 0.011052449544270834,
      "gpu_count": 0,
      "estimated_cost_dkk": 0.006202083333333332,
      "underutilized_cost_dkk": 0.0061335351202223025,
      "cpu_cost_dkk": 0.004134722222222222,
      "mem_cost_dkk": 0.006202083333333332,
      "gpu_cost_dkk": 0.0,
      "cost_bearer": "memory",
      "cost_bearer_cost_dkk": 0.006202083333333332,
      "cost_bearer_efficiency": 0.011052449544270834,
      "cost_bearer_waste_dkk": 0.0061335351202223025
    },
    {
      "report_date": "2024-06-27",
      "partition_name": "cpuqueue",
      "state": "COMPLETED",
      "alloc_cpus": 1,
      "elapsed_hours": 0.06166666666666667,
      "measured_cpu_efficiency": 0.47297297297297297,
      "memory_efficiency": 0.011503219604492188,
      "gpu_count": 0,
      "estimated_cost_dkk": 0.0060125000000000005,
      "underutilized_cost_dkk": 0.005943336892127991,
      "cpu_cost_dkk": 0.004008333333333333,
      "mem_cost_dkk": 0.0060125000000000005,
      "gpu_cost_dkk": 0.0,
      "cost_bearer": "memory",
      "cost_bearer_cost_dkk": 0.0060125000000000005,
      "cost_bearer_efficiency": 0.011503219604492188,
      "cost_bearer_waste_dkk": 0.005943336892127991
    },
    {
      "report_date": "2024-06-27",
      "partition_name": "cpuqueue",
      "state": "COMPLETED",
      "alloc_cpus": 1,
      "elapsed_hours": 0.06138888888888889,
      "measured_cpu_efficiency": 0.7692307692307693,
      "memory_efficiency": 0.011115392049153646,
      "gpu_count": 0,
      "estimated_cost_dkk": 0.005985416666666667,
      "underutilized_cost_dkk": 0.005918886413839128,
      "cpu_cost_dkk": 0.0039902777777777775,
      "mem_cost_dkk": 0.005985416666666667,
      "gpu_cost_dkk": 0.0,
      "cost_bearer": "memory",
      "cost_bearer_cost_dkk": 0.005985416666666667,
      "cost_bearer_efficiency": 0.011115392049153646,
      "cost_bearer_waste_dkk": 0.005918886413839128
    },
    {
      "report_date": "2024-06-27",
      "partition_name": "cpuqueue",
      "state": "COMPLETED",
      "alloc_cpus": 1,
      "elapsed_hours": 0.059722222222222225,
      "measured_cpu_efficiency": 0.6046511627906976,
      "memory_efficiency": 0.011664708455403646,
      "gpu_count": 0,
      "estimated_cost_dkk": 0.005822916666666667,
      "underutilized_cost_dkk": 0.005754994041389889,
      "cpu_cost_dkk": 0.003881944444444445,
      "mem_cost_dkk": 0.005822916666666667,
      "gpu_cost_dkk": 0.0,
      "cost_bearer": "memory",
      "cost_bearer_cost_dkk": 0.005822916666666667,
      "cost_bearer_efficiency": 0.011664708455403646,
      "cost_bearer_waste_dkk": 0.005754994041389889
    }
  ],
  "public_user_id": "usr_0457b537758a",
  "display_pseudonym": "Slate Juniper",
  "personal_route_token": "u_f3f2b63cd7a60e8227acb2e03c8c41ad",
  "percentile_position": {
    "overall": null,
    "cpu": null,
    "memory": null,
    "savings": null
  },
  "peer_comparisons": []
}
